Workbook

Sheet README
A1: S1 Data | Monthly analysis observations and Figure 2 supporting data
A3: Field | B3: Description
A4: Working paper | B4: Renminbi-denominated oil-price movements and inflation dynamics across China’s price system
A5: Main observations | B5: Monthly_338: 1998-01 through 2026-02; 338 monthly rows
A6: Customs observations | B6: Customs_134: 2015-01 through 2026-02; HS 27090000 only, 134 rows
A7: Figure 2 source | B7: Fig2_observations: long format reconstructed from author-supplied raw inputs, NOT the old private 7,774-row figure export
A8: Raw file fingerprint | B8: 10/10 primary input SHA256 match released repository config/raw_inputs.json
A9: Provenance | B9: Author-supplied 01_raw.zip, using original EIA/FRED/NBS/Customs series; third-party terms remain applicable
A10: Primary outcome | B10: Monthly change in year-on-year inflation, in percentage points, not month-on-month price inflation
A11: Shock variable | B11: 100 x calendar-month log change of Brent USD/barrel times CNY/USD
A12: Lag/lead policy | B12: Primary LP two oil-change and two outcome lags; h=0–12 with calendar-aware observations
A13: Missing data | B13: Blank means unavailable or undefined at transformation boundary; zeros are actual zeros
A14: Publication status | B14: Final supporting dataset for journal submission. Observation-level and sample consistency checks completed; full independent statistical re-estimation was not performed.
A15: Archive identity | B15: Supplementary file distinct from GitHub v2.0.0 / Zenodo DOI 10.5281/zenodo.23388839
A16: Do not label independent 39-model / MBB / full figure recreation as verified from this workbook; consult the repository VALIDATION.md.
A17: Files in this workbook are reconstructed observations. Recomputing regression tables requires the released analysis scripts and historical environment.
A18: Short-sample transformation boundary | B18: For the formal customs-sample stationary data, restrict the calendar to January 2015–February 2026 before computing differences. January 2015 is the transformation boundary. Full-calendar macroeconomic changes remain unchanged in Monthly_338.
A19: Estimation-sample indicators | B19: The link1_origin flag identifies the 130 Customs Link 1 months beginning in May 2015. Primary LP eligibility indicators refer only to the long-sample macroeconomic models and must not be substituted for customs-sample eligibility.

Sheet Monthly_338
A1: month | B1: brent_usd_per_bbl | C1: cny_per_usd | D1: oil_rmb_cny_per_bbl | E1: dlog_brent | F1: dlog_fx | G1: dlog_oil_rmb | H1: fuel_index_yoy | I1: ppi_index_yoy | J1: cpi_index_yoy | K1: d_fuel_power_inflation | L1: d_ppi_inflation | M1: d_cpi_inflation | N1: purchase_index_yoy | O1: indust_va_yoy | P1: indust_va_cum_yoy | Q1: lp_origin_h0 | R1: lp_origin_h3 | S1: lp_origin_h6 | T1: lp_origin_h12
A2: 1998-01 | B2: 15.19 | C2: 8.3094 | D2: =B2*C2 -> 126.21979 | E2: ="" | F2: ="" | G2: ="" | H2: 105.9 | I2: 98.7 | J2: 100.3 | K2: ="" | L2: ="" | M2: ="" | N2: 99.6 | Q2: =IF(ROW()>=5,1,0) -> 0 | R2: =IF(AND(ROW()>=5,ROW()+3<=339),1,0) -> 0 | S2: =IF(AND(ROW()>=5,ROW()+6<=339),1,0) -> 0 | T2: =IF(AND(ROW()>=5,ROW()+12<=339),1,0) -> 0
A3: 1998-02 | B3: 14.07 | C3: 8.3072 | D3: =B3*C3 -> 116.8823 | E3: =100*LN(B3/B2) -> -7.6592445 | F3: =100*LN(C3/C2) -> -0.026479545 | G3: =100*LN(D3/D2) -> -7.6857241 | H3: 101.5 | I3: 97.4 | J3: 99.9 | K3: =H3-H2 -> -4.4 | L3: =I3-I2 -> -1.3 | M3: =J3-J2 -> -0.4 | N3: 98.3 | Q3: =IF(ROW()>=5,1,0) -> 0 | R3: =IF(AND(ROW()>=5,ROW()+3<=339),1,0) -> 0 | S3: =IF(AND(ROW()>=5,ROW()+6<=339),1,0) -> 0 | T3: =IF(AND(ROW()>=5,ROW()+12<=339),1,0) -> 0
A4: 1998-03 | B4: 13.1 | C4: 8.3076 | D4: =B4*C4 -> 108.82956 | E4: =100*LN(B4/B3) -> -7.1432641 | F4: =100*LN(C4/C3) -> 0.0048149842 | G4: =100*LN(D4/D3) -> -7.1384491 | H4: 100.7 | I4: 96.8 | J4: 100.7 | K4: =H4-H3 -> -0.8 | L4: =I4-I3 -> -0.6 | M4: =J4-J3 -> 0.8 | N4: 97.7 | Q4: =IF(ROW()>=5,1,0) -> 0 | R4: =IF(AND(ROW()>=5,ROW()+3<=339),1,0) -> 0 | S4: =IF(AND(ROW()>=5,ROW()+6<=339),1,0) -> 0 | T4: =IF(AND(ROW()>=5,ROW()+12<=339),1,0) -> 0
A5: 1998-04 | B5: 13.53 | C5: 8.3058 | D5: =B5*C5 -> 112.37747 | E5: =100*LN(B5/B4) -> 3.2297212 | F5: =100*LN(C5/C4) -> -0.021669255 | G5: =100*LN(D5/D4) -> 3.2080519 | H5: 100.3 | I5: 96.3 | J5: 99.7 | K5: =H5-H4 -> -0.4 | L5: =I5-I4 -> -0.5 | M5: =J5-J4 -> -1 | N5: 97.3 | Q5: =IF(ROW()>=5,1,0) -> 1 | R5: =IF(AND(ROW()>=5,ROW()+3<=339),1,0) -> 1 | S5: =IF(AND(ROW()>=5,ROW()+6<=339),1,0) -> 1 | T5: =IF(AND(ROW()>=5,ROW()+12<=339),1,0) -> 1
A6: 1998-05 | B6: 14.36 | C6: 8.3084 | D6: =B6*C6 -> 119.30862 | E6: =100*LN(B6/B5) -> 5.9537121 | F6: =100*LN(C6/C5) -> 0.031298528 | G6: =100*LN(D6/D5) -> 5.9850107 | H6: 98.4 | I6: 95.5 | J6: 99 | K6: =H6-H5 -> -1.9 | L6: =I6-I5 -> -0.8 | M6: =J6-J5 -> -0.7 | N6: 94.7 | Q6: =IF(ROW()>=5,1,0) -> 1 | R6: =IF(AND(ROW()>=5,ROW()+3<=339),1,0) -> 1 | S6: =IF(AND(ROW()>=5,ROW()+6<=339),1,0) -> 1 | T6: =IF(AND(ROW()>=5,ROW()+12<=339),1,0) -> 1
A7: 1998-06 | B7: 12.21 | C7: 8.31 | D7: =B7*C7 -> 101.4651 | E7: =100*LN(B7/B6) -> -16.219128 | F7: =100*LN(C7/C6) -> 0.019255765 | G7: =100*LN(D7/D6) -> -16.199872 | H7: 98.4 | I7: 95.1 | J7: 98.7 | K7: =H7-H6 -> 0 | L7: =I7-I6 -> -0.4 | M7: =J7-J6 -> -0.3 | N7: 94.8 | Q7: =IF(ROW()>=5,1,0) -> 1 | R7: =IF(AND(ROW()>=5,ROW()+3<=339),1,0) -> 1 | S7: =IF(AND(ROW()>=5,ROW()+6<=339),1,0) -> 1 | T7: =IF(AND(ROW()>=5,ROW()+12<=339),1,0) -> 1
A8: 1998-07 | B8: 12.08 | C8: 8.31 | D8: =B8*C8 -> 100.3848 | E8: =100*LN(B8/B7) -> -1.0704096 | F8: =100*LN(C8/C7) -> 0 | G8: =100*LN(D8/D7) -> -1.0704096 | H8: 95.8 | I8: 95 | J8: 98.6 | K8: =H8-H7 -> -2.6 | L8: =I8-I7 -> -0.1 | M8: =J8-J7 -> -0.1 | N8: 94 | O8: 7.6 | P8: 7.8 | Q8: =IF(ROW()>=5,1,0) -> 1 | R8: =IF(AND(ROW()>=5,ROW()+3<=339),1,0) -> 1 | S8: =IF(AND(ROW()>=5,ROW()+6<=339),1,0) -> 1 | T8: =IF(AND(ROW()>=5,ROW()+12<=339),1,0) -> 1
A9: 1998-08 | B9: 11.91 | C9: 8.31 | D9: =B9*C9 -> 98.9721 | E9: =100*LN(B9/B8) -> -1.4172809 | F9: =100*LN(C9/C8) -> 0 | G9: =100*LN(D9/D8) -> -1.4172809 | H9: 95.7 | I9: 94.5 | J9: 98.6 | K9: =H9-H8 -> -0.1 | L9: =I9-I8 -> -0.5 | M9: =J9-J8 -> 0 | N9: 92.9 | O9: 7.9 | P9: 7.8 | Q9: =IF(ROW()>=5,1,0) -> 1 | R9: =IF(AND(ROW()>=5,ROW()+3<=339),1,0) -> 1 | S9: =IF(AND(ROW()>=5,ROW()+6<=339),1,0) -> 1 | T9: =IF(AND(ROW()>=5,ROW()+12<=339),1,0) -> 1
A10: 1998-09 | B10: 13.34 | C10: 8.3055 | D10: =B10*C10 -> 110.79537 | E10: =100*LN(B10/B9) -> 11.338866 | F10: =100*LN(C10/C9) -> -0.054166292 | G10: =100*LN(D10/D9) -> 11.284699 | H10: 95.7 | I10: 95.8 | J10: 98.5 | K10: =H10-H9 -> 0 | L10: =I10-I9 -> 1.3 | M10: =J10-J9 -> -0.1 | N10: 94.1 | O10: 10.2 | P10: 8 | Q10: =IF(ROW()>=5,1,0) -> 1 | R10: =IF(AND(ROW()>=5,ROW()+3<=339),1,0) -> 1 | S10: =IF(AND(ROW()>=5,ROW()+6<=339),1,0) -> 1 | T10: =IF(AND(ROW()>=5,ROW()+12<=339),1,0) -> 1
A11: 1998-10 | B11: 12.7 | C11: 8.2778 | D11: =B11*C11 -> 105.12806 | E11: =100*LN(B11/B10) -> -4.9165047 | F11: =100*LN(C11/C10) -> -0.33407133 | G11: =100*LN(D11/D10) -> -5.250576 | H11: 97 | I11: 94.3 | J11: 98.9 | K11: =H11-H10 -> 1.3 | L11: =I11-I10 -> -1.5 | M11: =J11-J10 -> 0.4 | N11: 93.9 | O11: 10.6 | P11: 8.2 | Q11: =IF(ROW()>=5,1,0) -> 1 | R11: =IF(AND(ROW()>=5,ROW()+3<=339),1,0) -> 1 | S11: =IF(AND(ROW()>=5,ROW()+6<=339),1,0) -> 1 | T11: =IF(AND(ROW()>=5,ROW()+12<=339),1,0) -> 1
A12: 1998-11 | B12: 11.04 | C12: 8.2778 | D12: =B12*C12 -> 91.386912 | E12: =100*LN(B12/B11) -> -14.007695 | F12: =100*LN(C12/C11) -> 0 | G12: =100*LN(D12/D11) -> -14.007695 | H12: 96.8 | I12: 94.6 | J12: 98.8 | K12: =H12-H11 -> -0.2 | L12: =I12-I11 -> 0.3 | M12: =J12-J11 -> -0.1 | N12: 93.9 | O12: 11 | P12: 8.5 | Q12: =IF(ROW()>=5,1,0) -> 1 | R12: =IF(AND(ROW()>=5,ROW()+3<=339),1,0) -> 1 | S12: =IF(AND(ROW()>=5,ROW()+6<=339),1,0) -> 1 | T12: =IF(AND(ROW()>=5,ROW()+12<=339),1,0) -> 1
A13: 1998-12 | B13: 9.82 | C13: 8.278 | D13: =B13*C13 -> 81.28996 | E13: =100*LN(B13/B12) -> -11.710392 | F13: =100*LN(C13/C12) -> 0.0024160717 | G13: =100*LN(D13/D12) -> -11.707976 | H13: 96.4 | I13: 96.2 | J13: 99 | K13: =H13-H12 -> -0.4 | L13: =I13-I12 -> 1.6 | M13: =J13-J12 -> 0.2 | N13: 93.9 | O13: 11.5 | P13: 8.8 | Q13: =IF(ROW()>=5,1,0) -> 1 | R13: =IF(AND(ROW()>=5,ROW()+3<=339),1,0) -> 1 | S13: =IF(AND(ROW()>=5,ROW()+6<=339),1,0) -> 1 | T13: =IF(AND(ROW()>=5,ROW()+12<=339),1,0) -> 1
A14: 1999-01 | B14: 11.11 | C14: 8.2789 | D14: =B14*C14 -> 91.978579 | E14: =100*LN(B14/B13) -> 12.342448 | F14: =100*LN(C14/C13) -> 0.0108716 | G14: =100*LN(D14/D13) -> 12.35332 | H14: 95.4 | I14: 95.1 | J14: 98.8 | K14: =H14-H13 -> -1 | L14: =I14-I13 -> -1.1 | M14: =J14-J13 -> -0.2 | N14: 92.7 | Q14: =IF(ROW()>=5,1,0) -> 1 | R14: =IF(AND(ROW()>=5,ROW()+3<=339),1,0) -> 1 | S14: =IF(AND(ROW()>=5,ROW()+6<=339),1,0) -> 1 | T14: =IF(AND(ROW()>=5,ROW()+12<=339),1,0) -> 1
A15: 1999-02 | B15: 10.27 | C15: 8.2781 | D15: =B15*C15 -> 85.016087 | E15: =100*LN(B15/B14) -> -7.861858 | F15: =100*LN(C15/C14) -> -0.0096635864 | G15: =100*LN(D15/D14) -> -7.8715216 | H15: 94.3 | I15: 95.1 | J15: 98.7 | K15: =H15-H14 -> -1.1 | L15: =I15-I14 -> 0 | M15: =J15-J14 -> -0.1 | N15: 93.2 | O15: 2.1 | P15: 10.6 | Q15: =IF(ROW()>=5,1,0) -> 1 | R15: =IF(AND(ROW()>=5,ROW()+3<=339),1,0) -> 1 | S15: =IF(AND(ROW()>=5,ROW()+6<=339),1,0) -> 1 | T15: =IF(AND(ROW()>=5,ROW()+12<=339),1,0) -> 1
A16: 1999-03 | B16: 12.51 | C16: 8.2792 | D16: =B16*C16 -> 103.57279 | E16: =100*LN(B16/B15) -> 19.73013 | F16: =100*LN(C16/C15) -> 0.013287191 | G16: =100*LN(D16/D15) -> 19.743417 | H16: 95.3 | I16: 95.4 | J16: 98.2 | K16: =H16-H15 -> 1 | L16: =I16-I15 -> 0.3 | M16: =J16-J15 -> -0.5 | N16: 93.5 | O16: 9 | P16: 10.1 | Q16: =IF(ROW()>=5,1,0) -> 1 | R16: =IF(AND(ROW()>=5,ROW()+3<=339),1,0) -> 1 | S16: =IF(AND(ROW()>=5,ROW()+6<=339),1,0) -> 1 | T16: =IF(AND(ROW()>=5,ROW()+12<=339),1,0) -> 1
A17: 1999-04 | B17: 15.29 | C17: 8.2792 | D17: =B17*C17 -> 126.58897 | E17: =100*LN(B17/B16) -> 20.06707 | F17: =100*LN(C17/C16) -> 0 | G17: =100*LN(D17/D16) -> 20.06707 | H17: 96.1 | I17: 96.1 | J17: 97.8 | K17: =H17-H16 -> 0.8 | L17: =I17-I16 -> 0.7 | M17: =J17-J16 -> -0.4 | N17: 93.7 | O17: 9.1 | P17: 9.7 | Q17: =IF(ROW()>=5,1,0) -> 1 | R17: =IF(AND(ROW()>=5,ROW()+3<=339),1,0) -> 1 | S17: =IF(AND(ROW()>=5,ROW()+6<=339),1,0) -> 1 | T17: =IF(AND(ROW()>=5,ROW()+12<=339),1,0) -> 1
A18: 1999-05 | B18: 15.23 | C18: 8.2785 | D18: =B18*C18 -> 126.08155 | E18: =100*LN(B18/B17) -> -0.3931853 | F18: =100*LN(C18/C17) -> -0.0084552806 | G18: =100*LN(D18/D17) -> -0.40164058 | H18: 98.3 | I18: 96.6 | J18: 97.8 | K18: =H18-H17 -> 2.2 | L18: =I18-I17 -> 0.5 | M18: =J18-J17 -> 0 | N18: 95.1 | O18: 8.9 | P18: 9.5 | Q18: =IF(ROW()>=5,1,0) -> 1 | R18: =IF(AND(ROW()>=5,ROW()+3<=339),1,0) -> 1 | S18: =IF(AND(ROW()>=5,ROW()+6<=339),1,0) -> 1 | T18: =IF(AND(ROW()>=5,ROW()+12<=339),1,0) -> 1
A19: 1999-06 | B19: 15.86 | C19: 8.278 | D19: =B19*C19 -> 131.28908 | E19: =100*LN(B19/B18) -> 4.0533049 | F19: =100*LN(C19/C18) -> -0.0060399239 | G19: =100*LN(D19/D18) -> 4.047265 | H19: 99.4 | I19: 96.4 | J19: 97.9 | K19: =H19-H18 -> 1.1 | L19: =I19-I18 -> -0.2 | M19: =J19-J18 -> 0.1 | N19: 95.1 | O19: 9.1 | P19: 9.4 | Q19: =IF(ROW()>=5,1,0) -> 1 | R19: =IF(AND(ROW()>=5,ROW()+3<=339),1,0) -> 1 | S19: =IF(AND(ROW()>=5,ROW()+6<=339),1,0) -> 1 | T19: =IF(AND(ROW()>=5,ROW()+12<=339),1,0) -> 1
A20: 1999-07 | B20: 19.08 | C20: 8.2776 | D20: =B20*C20 -> 157.93661 | E20: =100*LN(B20/B19) -> 18.484045 | F20: =100*LN(C20/C19) -> -0.0048322018 | G20: =100*LN(D20/D19) -> 18.479213 | H20: 100.3 | I20: 97.5 | J20: 98.6 | K20: =H20-H19 -> 0.9 | L20: =I20-I19 -> 1.1 | M20: =J20-J19 -> 0.7 | N20: 96.6 | O20: 9.3 | P20: 9.4 | Q20: =IF(ROW()>=5,1,0) -> 1 | R20: =IF(AND(ROW()>=5,ROW()+3<=339),1,0) -> 1 | S20: =IF(AND(ROW()>=5,ROW()+6<=339),1,0) -> 1 | T20: =IF(AND(ROW()>=5,ROW()+12<=339),1,0) -> 1
A21: 1999-08 | B21: 20.22 | C21: 8.2772 | D21: =B21*C21 -> 167.36498 | E21: =100*LN(B21/B20) -> 5.8031548 | F21: =100*LN(C21/C20) -> -0.0048324353 | G21: =100*LN(D21/D20) -> 5.7983223 | H21: 103.1 | I21: 97.7 | J21: 98.7 | K21: =H21-H20 -> 2.8 | L21: =I21-I20 -> 0.2 | M21: =J21-J20 -> 0.1 | N21: 96.7 | O21: 9.5 | P21: 9.4 | Q21: =IF(ROW()>=5,1,0) -> 1 | R21: =IF(AND(ROW()>=5,ROW()+3<=339),1,0) -> 1 | S21: =IF(AND(ROW()>=5,ROW()+6<=339),1,0) -> 1 | T21: =IF(AND(ROW()>=5,ROW()+12<=339),1,0) -> 1
A22: 1999-09 | B22: 22.54 | C22: 8.2774 | D22: =B22*C22 -> 186.5726 | E22: =100*LN(B22/B21) -> 10.86193 | F22: =100*LN(C22/C21) -> 0.0024162468 | G22: =100*LN(D22/D21) -> 10.864346 | H22: 103.1 | I22: 97.9 | J22: 99.2 | K22: =H22-H21 -> 0 | L22: =I22-I21 -> 0.2 | M22: =J22-J21 -> 0.5 | N22: 98.2 | O22: 8.2 | P22: 9.3 | Q22: =IF(ROW()>=5,1,0) -> 1 | R22: =IF(AND(ROW()>=5,ROW()+3<=339),1,0) -> 1 | S22: =IF(AND(ROW()>=5,ROW()+6<=339),1,0) -> 1 | T22: =IF(AND(ROW()>=5,ROW()+12<=339),1,0) -> 1
A23: 1999-10 | B23: 22 | C23: 8.2775 | D23: =B23*C23 -> 182.105 | E23: =100*LN(B23/B22) -> -2.4249055 | F23: =100*LN(C23/C22) -> 0.0012081015 | G23: =100*LN(D23/D22) -> -2.4236974 | H23: 107.1 | I23: 99.3 | J23: 99.4 | K23: =H23-H22 -> 4 | L23: =I23-I22 -> 1.4 | M23: =J23-J22 -> 0.2 | N23: 98.9 | O23: 7 | P23: 9.1 | Q23: =IF(ROW()>=5,1,0) -> 1 | R23: =IF(AND(ROW()>=5,ROW()+3<=339),1,0) -> 1 | S23: =IF(AND(ROW()>=5,ROW()+6<=339),1,0) -> 1 | T23: =IF(AND(ROW()>=5,ROW()+12<=339),1,0) -> 1
A24: 1999-11 | B24: 24.58 | C24: 8.2782 | D24: =B24*C24 -> 203.47816 | E24: =100*LN(B24/B23) -> 11.089065 | F24: =100*LN(C24/C23) -> 0.0084563021 | G24: =100*LN(D24/D23) -> 11.097521 | H24: 104.6 | I24: 98.9 | J24: 99.1 | K24: =H24-H23 -> -2.5 | L24: =I24-I23 -> -0.4 | M24: =J24-J23 -> -0.3 | N24: 98.3 | O24: 7.6 | P24: 9 | Q24: =IF(ROW()>=5,1,0) -> 1 | R24: =IF(AND(ROW()>=5,ROW()+3<=339),1,0) -> 1 | S24: =IF(AND(ROW()>=5,ROW()+6<=339),1,0) -> 1 | T24: =IF(AND(ROW()>=5,ROW()+12<=339),1,0) -> 1
A25: 1999-12 | B25: 25.47 | C25: 8.2794 | D25: =B25*C25 -> 210.87632 | E25: =100*LN(B25/B24) -> 3.5568185 | F25: =100*LN(C25/C24) -> 0.014494854 | G25: =100*LN(D25/D24) -> 3.5713133 | H25: 110.3 | I25: 99.2 | J25: 99 | K25: =H25-H24 -> 5.7 | L25: =I25-I24 -> 0.3 | M25: =J25-J24 -> -0.1 | N25: 100.8 | O25: 7.4 | P25: 8.9 | Q25: =IF(ROW()>=5,1,0) -> 1 | R25: =IF(AND(ROW()>=5,ROW()+3<=339),1,0) -> 1 | S25: =IF(AND(ROW()>=5,ROW()+6<=339),1,0) -> 1 | T25: =IF(AND(ROW()>=5,ROW()+12<=339),1,0) -> 1
A26: 2000-01 | B26: 25.51 | C26: 8.2792 | D26: =B26*C26 -> 211.20239 | E26: =100*LN(B26/B25) -> 0.15692432 | F26: =100*LN(C26/C25) -> -0.0024156632 | G26: =100*LN(D26/D25) -> 0.15450865 | H26: 113.2 | I26: 100 | J26: 99.8 | K26: =H26-H25 -> 2.9 | L26: =I26-I25 -> 0.8 | M26: =J26-J25 -> 0.8 | N26: 102.1 | Q26: =IF(ROW()>=5,1,0) -> 1 | R26: =IF(AND(ROW()>=5,ROW()+3<=339),1,0) -> 1 | S26: =IF(AND(ROW()>=5,ROW()+6<=339),1,0) -> 1 | T26: =IF(AND(ROW()>=5,ROW()+12<=339),1,0) -> 1
A27: 2000-02 | B27: 27.78 | C27: 8.2781 | D27: =B27*C27 -> 229.96562 | E27: =100*LN(B27/B26) -> 8.5245805 | F27: =100*LN(C27/C26) -> -0.013287191 | G27: =100*LN(D27/D26) -> 8.5112933 | H27: 114.1 | I27: 101 | J27: 100.7 | K27: =H27-H26 -> 0.9 | L27: =I27-I26 -> 1 | M27: =J27-J26 -> 0.9 | N27: 103.6 | O27: 12 | P27: 10.4 | Q27: =IF(ROW()>=5,1,0) -> 1 | R27: =IF(AND(ROW()>=5,ROW()+3<=339),1,0) -> 1 | S27: =IF(AND(ROW()>=5,ROW()+6<=339),1,0) -> 1 | T27: =IF(AND(ROW()>=5,ROW()+12<=339),1,0) -> 1
A28: 2000-03 | B28: 27.49 | C28: 8.2786 | D28: =B28*C28 -> 227.57871 | E28: =100*LN(B28/B27) -> -1.0494035 | F28: =100*LN(C28/C27) -> 0.0060398509 | G28: =100*LN(D28/D27) -> -1.0433637 | H28: 115.7 | I28: 101.9 | J28: 99.8 | K28: =H28-H27 -> 1.6 | L28: =I28-I27 -> 0.9 | M28: =J28-J27 -> -0.9 | N28: 104.8 | O28: 11.9 | P28: 10.7 | Q28: =IF(ROW()>=5,1,0) -> 1 | R28: =IF(AND(ROW()>=5,ROW()+3<=339),1,0) -> 1 | S28: =IF(AND(ROW()>=5,ROW()+6<=339),1,0) -> 1 | T28: =IF(AND(ROW()>=5,ROW()+12<=339),1,0) -> 1
A29: 2000-04 | B29: 22.76 | C29: 8.2793 | D29: =B29*C29 -> 188.43687 | E29: =100*LN(B29/B28) -> -18.881769 | F29: =100*LN(C29/C28) -> 0.0084551785 | G29: =100*LN(D29/D28) -> -18.873314 | H29: 116.5 | I29: 102.6 | J29: 99.7 | K29: =H29-H28 -> 0.8 | L29: =I29-I28 -> 0.7 | M29: =J29-J28 -> -0.1 | N29: 105.3 | O29: 11.4 | P29: 10.9 | Q29: =IF(ROW()>=5,1,0) -> 1 | R29: =IF(AND(ROW()>=5,ROW()+3<=339),1,0) -> 1 | S29: =IF(AND(ROW()>=5,ROW()+6<=339),1,0) -> 1 | T29: =IF(AND(ROW()>=5,ROW()+12<=339),1,0) -> 1
A30: 2000-05 | B30: 27.74 | C30: 8.2781 | D30: =B30*C30 -> 229.63449 | E30: =100*LN(B30/B29) -> 19.787081 | F30: =100*LN(C30/C29) -> -0.014495029 | G30: =100*LN(D30/D29) -> 19.772586 | H30: 111.9 | I30: 102.5 | J30: 100.1 | K30: =H30-H29 -> -4.6 | L30: =I30-I29 -> -0.1 | M30: =J30-J29 -> 0.4 | N30: 105.5 | O30: 11.5 | P30: 11 | Q30: =IF(ROW()>=5,1,0) -> 1 | R30: =IF(AND(ROW()>=5,ROW()+3<=339),1,0) -> 1 | S30: =IF(AND(ROW()>=5,ROW()+6<=339),1,0) -> 1 | T30: =IF(AND(ROW()>=5,ROW()+12<=339),1,0) -> 1
A31: 2000-06 | B31: 29.8 | C31: 8.2772 | D31: =B31*C31 -> 246.66056 | E31: =100*LN(B31/B30) -> 7.1632979 | F31: =100*LN(C31/C30) -> -0.010872651 | G31: =100*LN(D31/D30) -> 7.1524252 | H31: 114.2 | I31: 102.9 | J31: 100.5 | K31: =H31-H30 -> 2.3 | L31: =I31-I30 -> 0.4 | M31: =J31-J30 -> 0.4 | N31: 107.1 | O31: 12.2 | P31: 11.2 | Q31: =IF(ROW()>=5,1,0) -> 1 | R31: =IF(AND(ROW()>=5,ROW()+3<=339),1,0) -> 1 | S31: =IF(AND(ROW()>=5,ROW()+6<=339),1,0) -> 1 | T31: =IF(AND(ROW()>=5,ROW()+12<=339),1,0) -> 1
A32: 2000-07 | B32: 28.68 | C32: 8.2794 | D32: =B32*C32 -> 237.45319 | E32: =100*LN(B32/B31) -> -3.8308378 | F32: =100*LN(C32/C31) -> 0.026575505 | G32: =100*LN(D32/D31) -> -3.8042623 | H32: 115.2 | I32: 104.5 | J32: 100.5 | K32: =H32-H31 -> 1 | L32: =I32-I31 -> 1.6 | M32: =J32-J31 -> 0 | N32: 108.6 | O32: 12.8 | P32: 11.4 | Q32: =IF(ROW()>=5,1,0) -> 1 | R32: =IF(AND(ROW()>=5,ROW()+3<=339),1,0) -> 1 | S32: =IF(AND(ROW()>=5,ROW()+6<=339),1,0) -> 1 | T32: =IF(AND(ROW()>=5,ROW()+12<=339),1,0) -> 1
A33: 2000-08 | B33: 30.2 | C33: 8.2796 | D33: =B33*C33 -> 250.04392 | E33: =100*LN(B33/B32) -> 5.1641909 | F33: =100*LN(C33/C32) -> 0.0024156048 | G33: =100*LN(D33/D32) -> 5.1666065 | H33: 117.8 | I33: 103.9 | J33: 100.3 | K33: =H33-H32 -> 2.6 | L33: =I33-I32 -> -0.6 | M33: =J33-J32 -> -0.2 | N33: 104.6 | O33: 12.8 | P33: 11.6 | Q33: =IF(ROW()>=5,1,0) -> 1 | R33: =IF(AND(ROW()>=5,ROW()+3<=339),1,0) -> 1 | S33: =IF(AND(ROW()>=5,ROW()+6<=339),1,0) -> 1 | T33: =IF(AND(ROW()>=5,ROW()+12<=339),1,0) -> 1
A34: 2000-09 | B34: 33.14 | C34: 8.2785 | D34: =B34*C34 -> 274.34949 | E34: =100*LN(B34/B33) -> 9.2899088 | F34: =100*LN(C34/C33) -> -0.013286549 | G34: =100*LN(D34/D33) -> 9.2766222 | H34: 117.6 | I34: 103.7 | J34: 100 | K34: =H34-H33 -> -0.2 | L34: =I34-I33 -> -0.2 | M34: =J34-J33 -> -0.3 | N34: 105.1 | O34: 12 | P34: 11.6 | Q34: =IF(ROW()>=5,1,0) -> 1 | R34: =IF(AND(ROW()>=5,ROW()+3<=339),1,0) -> 1 | S34: =IF(AND(ROW()>=5,ROW()+6<=339),1,0) -> 1 | T34: =IF(AND(ROW()>=5,ROW()+12<=339),1,0) -> 1
A35: 2000-10 | B35: 30.96 | C35: 8.2785 | D35: =B35*C35 -> 256.30236 | E35: =100*LN(B35/B34) -> -6.8044963 | F35: =100*LN(C35/C34) -> 0 | G35: =100*LN(D35/D34) -> -6.8044963 | H35: 118.1 | I35: 103.6 | J35: 100 | K35: =H35-H34 -> 0.5 | L35: =I35-I34 -> -0.1 | M35: =J35-J34 -> 0 | N35: 105.2 | O35: 11.4 | P35: 11.6 | Q35: =IF(ROW()>=5,1,0) -> 1 | R35: =IF(AND(ROW()>=5,ROW()+3<=339),1,0) -> 1 | S35: =IF(AND(ROW()>=5,ROW()+6<=339),1,0) -> 1 | T35: =IF(AND(ROW()>=5,ROW()+12<=339),1,0) -> 1
A36: 2000-11 | B36: 32.55 | C36: 8.2774 | D36: =B36*C36 -> 269.42937 | E36: =100*LN(B36/B35) -> 5.008132 | F36: =100*LN(C36/C35) -> -0.013288314 | G36: =100*LN(D36/D35) -> 4.9948437 | H36: 116.7 | I36: 103.5 | J36: 101.3 | K36: =H36-H35 -> -1.4 | L36: =I36-I35 -> -0.1 | M36: =J36-J35 -> 1.3 | N36: 105 | O36: 10.6 | P36: 11.5 | Q36: =IF(ROW()>=5,1,0) -> 1 | R36: =IF(AND(ROW()>=5,ROW()+3<=339),1,0) -> 1 | S36: =IF(AND(ROW()>=5,ROW()+6<=339),1,0) -> 1 | T36: =IF(AND(ROW()>=5,ROW()+12<=339),1,0) -> 1
A37: 2000-12 | B37: 25.66 | C37: 8.2771 | D37: =B37*C37 -> 212.39039 | E37: =100*LN(B37/B36) -> -23.784401 | F37: =100*LN(C37/C36) -> -0.0036243922 | G37: =100*LN(D37/D36) -> -23.788025 | H37: 113.5 | I37: 102.8 | J37: 101.5 | K37: =H37-H36 -> -3.2 | L37: =I37-I36 -> -0.7 | M37: =J37-J36 -> 0.2 | N37: 104.7 | O37: 10.4 | P37: 11.4 | Q37: =IF(ROW()>=5,1,0) -> 1 | R37: =IF(AND(ROW()>=5,ROW()+3<=339),1,0) -> 1 | S37: =IF(AND(ROW()>=5,ROW()+6<=339),1,0) -> 1 | T37: =IF(AND(ROW()>=5,ROW()+12<=339),1,0) -> 1
A38: 2001-01 | B38: 25.62 | C38: 8.2776 | D38: =B38*C38 -> 212.07211 | E38: =100*LN(B38/B37) -> -0.15600627 | F38: =100*LN(C38/C37) -> 0.0060405806 | G38: =100*LN(D38/D37) -> -0.14996569 | H38: 110 | I38: 101.4 | J38: 101.2 | K38: =H38-H37 -> -3.5 | L38: =I38-I37 -> -1.4 | M38: =J38-J37 -> -0.3 | N38: 103.6 | Q38: =IF(ROW()>=5,1,0) -> 1 | R38: =IF(AND(ROW()>=5,ROW()+3<=339),1,0) -> 1 | S38: =IF(AND(ROW()>=5,ROW()+6<=339),1,0) -> 1 | T38: =IF(AND(ROW()>=5,ROW()+12<=339),1,0) -> 1
A39: 2001-02 | B39: 27.5 | C39: 8.2771 | D39: =B39*C39 -> 227.62025 | E39: =100*LN(B39/B38) -> 7.0812708 | F39: =100*LN(C39/C38) -> -0.0060405806 | G39: =100*LN(D39/D38) -> 7.0752302 | H39: 105.9 | I39: 100.9 | J39: 100 | K39: =H39-H38 -> -4.1 | L39: =I39-I38 -> -0.5 | M39: =J39-J38 -> -1.2 | N39: 102.7 | O39: 19 | P39: 10.2 | Q39: =IF(ROW()>=5,1,0) -> 1 | R39: =IF(AND(ROW()>=5,ROW()+3<=339),1,0) -> 1 | S39: =IF(AND(ROW()>=5,ROW()+6<=339),1,0) -> 1 | T39: =IF(AND(ROW()>=5,ROW()+12<=339),1,0) -> 1
A40: 2001-03 | B40: 24.5 | C40: 8.2775 | D40: =B40*C40 -> 202.79875 | E40: =100*LN(B40/B39) -> -11.551289 | F40: =100*LN(C40/C39) -> 0.0048324937 | G40: =100*LN(D40/D39) -> -11.546456 | H40: 104.3 | I40: 100.2 | J40: 100.8 | K40: =H40-H39 -> -1.6 | L40: =I40-I39 -> -0.7 | M40: =J40-J39 -> 0.8 | N40: 102.1 | O40: 12.1 | P40: 11.2 | Q40: =IF(ROW()>=5,1,0) -> 1 | R40: =IF(AND(ROW()>=5,ROW()+3<=339),1,0) -> 1 | S40: =IF(AND(ROW()>=5,ROW()+6<=339),1,0) -> 1 | T40: =IF(AND(ROW()>=5,ROW()+12<=339),1,0) -> 1
A41: 2001-04 | B41: 25.66 | C41: 8.2771 | D41: =B41*C41 -> 212.39039 | E41: =100*LN(B41/B40) -> 4.6260242 | F41: =100*LN(C41/C40) -> -0.0048324937 | G41: =100*LN(D41/D40) -> 4.6211917 | H41: 102.7 | I41: 99.9 | J41: 101.6 | K41: =H41-H40 -> -1.6 | L41: =I41-I40 -> -0.3 | M41: =J41-J40 -> 0.8 | N41: 100.9 | O41: 11.5 | P41: 11.3 | Q41: =IF(ROW()>=5,1,0) -> 1 | R41: =IF(AND(ROW()>=5,ROW()+3<=339),1,0) -> 1 | S41: =IF(AND(ROW()>=5,ROW()+6<=339),1,0) -> 1 | T41: =IF(AND(ROW()>=5,ROW()+12<=339),1,0) -> 1
A42: 2001-05 | B42: 28.31 | C42: 8.277 | D42: =B42*C42 -> 234.32187 | E42: =100*LN(B42/B41) -> 9.828174 | F42: =100*LN(C42/C41) -> -0.0012081599 | G42: =100*LN(D42/D41) -> 9.8269658 | H42: 104.4 | I42: 99.8 | J42: 101.7 | K42: =H42-H41 -> 1.7 | L42: =I42-I41 -> -0.1 | M42: =J42-J41 -> 0.1 | N42: 101.1 | O42: 10.2 | P42: 11.1 | Q42: =IF(ROW()>=5,1,0) -> 1 | R42: =IF(AND(ROW()>=5,ROW()+3<=339),1,0) -> 1 | S42: =IF(AND(ROW()>=5,ROW()+6<=339),1,0) -> 1 | T42: =IF(AND(ROW()>=5,ROW()+12<=339),1,0) -> 1
A43: 2001-06 | B43: 27.85 | C43: 8.277 | D43: =B43*C43 -> 230.51445 | E43: =100*LN(B43/B42) -> -1.6382133 | F43: =100*LN(C43/C42) -> 0 | G43: =100*LN(D43/D42) -> -1.6382133 | H43: 103.2 | I43: 99.4 | J43: 101.4 | K43: =H43-H42 -> -1.2 | L43: =I43-I42 -> -0.4 | M43: =J43-J42 -> -0.3 | N43: 100.5 | O43: 10.1 | P43: 11 | Q43: =IF(ROW()>=5,1,0) -> 1 | R43: =IF(AND(ROW()>=5,ROW()+3<=339),1,0) -> 1 | S43: =IF(AND(ROW()>=5,ROW()+6<=339),1,0) -> 1 | T43: =IF(AND(ROW()>=5,ROW()+12<=339),1,0) -> 1
A44: 2001-07 | B44: 24.61 | C44: 8.2769 | D44: =B44*C44 -> 203.69451 | E44: =100*LN(B44/B43) -> -12.36801 | F44: =100*LN(C44/C43) -> -0.0012081745 | G44: =100*LN(D44/D43) -> -12.369218 | H44: 100.8 | I44: 98.7 | J44: 101.5 | K44: =H44-H43 -> -2.4 | L44: =I44-I43 -> -0.7 | M44: =J44-J43 -> 0.1 | N44: 99.6 | O44: 8.1 | P44: 10.7 | Q44: =IF(ROW()>=5,1,0) -> 1 | R44: =IF(AND(ROW()>=5,ROW()+3<=339),1,0) -> 1 | S44: =IF(AND(ROW()>=5,ROW()+6<=339),1,0) -> 1 | T44: =IF(AND(ROW()>=5,ROW()+12<=339),1,0) -> 1
A45: 2001-08 | B45: 25.68 | C45: 8.277 | D45: =B45*C45 -> 212.55336 | E45: =100*LN(B45/B44) -> 4.2559614 | F45: =100*LN(C45/C44) -> 0.0012081745 | G45: =100*LN(D45/D44) -> 4.2571696 | H45: 98.8 | I45: 98 | J45: 101 | K45: =H45-H44 -> -2 | L45: =I45-I44 -> -0.7 | M45: =J45-J44 -> -0.5 | N45: 98.7 | O45: 8.1 | P45: 10.4 | Q45: =IF(ROW()>=5,1,0) -> 1 | R45: =IF(AND(ROW()>=5,ROW()+3<=339),1,0) -> 1 | S45: =IF(AND(ROW()>=5,ROW()+6<=339),1,0) -> 1 | T45: =IF(AND(ROW()>=5,ROW()+12<=339),1,0) -> 1
A46: 2001-09 | B46: 25.62 | C46: 8.2768 | D46: =B46*C46 -> 212.05162 | E46: =100*LN(B46/B45) -> -0.23391824 | F46: =100*LN(C46/C45) -> -0.0024163636 | G46: =100*LN(D46/D45) -> -0.2363346 | H46: 98.1 | I46: 97.1 | J46: 99.9 | K46: =H46-H45 -> -0.7 | L46: =I46-I45 -> -0.9 | M46: =J46-J45 -> -1.1 | N46: 98.2 | O46: 9.5 | P46: 10.3 | Q46: =IF(ROW()>=5,1,0) -> 1 | R46: =IF(AND(ROW()>=5,ROW()+3<=339),1,0) -> 1 | S46: =IF(AND(ROW()>=5,ROW()+6<=339),1,0) -> 1 | T46: =IF(AND(ROW()>=5,ROW()+12<=339),1,0) -> 1
A47: 2001-10 | B47: 20.54 | C47: 8.2768 | D47: =B47*C47 -> 170.00547 | E47: =100*LN(B47/B46) -> -22.099909 | F47: =100*LN(C47/C46) -> 0 | G47: =100*LN(D47/D46) -> -22.099909 | H47: 96.7 | I47: 96.9 | J47: 100.2 | K47: =H47-H46 -> -1.4 | L47: =I47-I46 -> -0.2 | M47: =J47-J46 -> 0.3 | N47: 97.5 | O47: 8.8 | P47: 10.2 | Q47: =IF(ROW()>=5,1,0) -> 1 | R47: =IF(AND(ROW()>=5,ROW()+3<=339),1,0) -> 1 | S47: =IF(AND(ROW()>=5,ROW()+6<=339),1,0) -> 1 | T47: =IF(AND(ROW()>=5,ROW()+12<=339),1,0) -> 1
A48: 2001-11 | B48: 18.8 | C48: 8.2769 | D48: =B48*C48 -> 155.60572 | E48: =100*LN(B48/B47) -> -8.8517335 | F48: =100*LN(C48/C47) -> 0.0012081891 | G48: =100*LN(D48/D47) -> -8.8505253 | H48: 94.7 | I48: 96.3 | J48: 99.7 | K48: =H48-H47 -> -2 | L48: =I48-I47 -> -0.6 | M48: =J48-J47 -> -0.5 | N48: 96.5 | O48: 7.9 | P48: 10 | Q48: =IF(ROW()>=5,1,0) -> 1 | R48: =IF(AND(ROW()>=5,ROW()+3<=339),1,0) -> 1 | S48: =IF(AND(ROW()>=5,ROW()+6<=339),1,0) -> 1 | T48: =IF(AND(ROW()>=5,ROW()+12<=339),1,0) -> 1
A49: 2001-12 | B49: 18.71 | C49: 8.2764 | D49: =B49*C49 -> 154.85144 | E49: =100*LN(B49/B48) -> -0.47987295 | F49: =100*LN(C49/C48) -> -0.0060410915 | G49: =100*LN(D49/D48) -> -0.48591405 | H49: 94.1 | I49: 96 | J49: 99.7 | K49: =H49-H48 -> -0.6 | L49: =I49-I48 -> -0.3 | M49: =J49-J48 -> 0 | N49: 95.9 | O49: 8.7 | P49: 9.9 | Q49: =IF(ROW()>=5,1,0) -> 1 | R49: =IF(AND(ROW()>=5,ROW()+3<=339),1,0) -> 1 | S49: =IF(AND(ROW()>=5,ROW()+6<=339),1,0) -> 1 | T49: =IF(AND(ROW()>=5,ROW()+12<=339),1,0) -> 1
A50: 2002-01 | B50: 19.42 | C50: 8.2771 | D50: =B50*C50 -> 160.74128 | E50: =100*LN(B50/B49) -> 3.7245323 | F50: =100*LN(C50/C49) -> 0.0084574259 | G50: =100*LN(D50/D49) -> 3.7329897 | H50: 94.1 | I50: 96 | J50: 99 | K50: =H50-H49 -> 0 | L50: =I50-I49 -> 0 | M50: =J50-J49 -> -0.7 | N50: 95.1 | Q50: =IF(ROW()>=5,1,0) -> 1 | R50: =IF(AND(ROW()>=5,ROW()+3<=339),1,0) -> 1 | S50: =IF(AND(ROW()>=5,ROW()+6<=339),1,0) -> 1 | T50: =IF(AND(ROW()>=5,ROW()+12<=339),1,0) -> 1
A51: 2002-02 | B51: 20.28 | C51: 8.2767 | D51: =B51*C51 -> 167.85148 | E51: =100*LN(B51/B50) -> 4.3331716 | F51: =100*LN(C51/C50) -> -0.0048327272 | G51: =100*LN(D51/D50) -> 4.3283389 | H51: 95.3 | I51: 95.9 | J51: 100 | K51: =H51-H50 -> 1.2 | L51: =I51-I50 -> -0.1 | M51: =J51-J50 -> 1 | N51: 95.3 | O51: 2.7 | P51: 10.9 | Q51: =IF(ROW()>=5,1,0) -> 1 | R51: =IF(AND(ROW()>=5,ROW()+3<=339),1,0) -> 1 | S51: =IF(AND(ROW()>=5,ROW()+6<=339),1,0) -> 1 | T51: =IF(AND(ROW()>=5,ROW()+12<=339),1,0) -> 1
A52: 2002-03 | B52: 23.7 | C52: 8.2773 | D52: =B52*C52 -> 196.17201 | E52: =100*LN(B52/B51) -> 15.583987 | F52: =100*LN(C52/C51) -> 0.0072490033 | G52: =100*LN(D52/D51) -> 15.591236 | H52: 95.8 | I52: 96 | J52: 99.2 | K52: =H52-H51 -> 0.5 | L52: =I52-I51 -> 0.1 | M52: =J52-J51 -> -0.8 | N52: 95.4 | O52: 10.9 | P52: 10.9 | Q52: =IF(ROW()>=5,1,0) -> 1 | R52: =IF(AND(ROW()>=5,ROW()+3<=339),1,0) -> 1 | S52: =IF(AND(ROW()>=5,ROW()+6<=339),1,0) -> 1 | T52: =IF(AND(ROW()>=5,ROW()+12<=339),1,0) -> 1
A53: 2002-04 | B53: 25.73 | C53: 8.2772 | D53: =B53*C53 -> 212.97236 | E53: =100*LN(B53/B52) -> 8.2182578 | F53: =100*LN(C53/C52) -> -0.0012081307 | G53: =100*LN(D53/D52) -> 8.2170497 | H53: 98.2 | I53: 96.9 | J53: 98.7 | K53: =H53-H52 -> 2.4 | L53: =I53-I52 -> 0.9 | M53: =J53-J52 -> -0.5 | N53: 96.2 | O53: 12.1 | P53: 11.2 | Q53: =IF(ROW()>=5,1,0) -> 1 | R53: =IF(AND(ROW()>=5,ROW()+3<=339),1,0) -> 1 | S53: =IF(AND(ROW()>=5,ROW()+6<=339),1,0) -> 1 | T53: =IF(AND(ROW()>=5,ROW()+12<=339),1,0) -> 1
A54: 2002-05 | B54: 25.35 | C54: 8.277 | D54: =B54*C54 -> 209.82195 | E54: =100*LN(B54/B53) -> -1.4878896 | F54: =100*LN(C54/C53) -> -0.0024163052 | G54: =100*LN(D54/D53) -> -1.4903059 | H54: 100.3 | I54: 97.4 | J54: 98.9 | K54: =H54-H53 -> 2.1 | L54: =I54-I53 -> 0.5 | M54: =J54-J53 -> 0.2 | N54: 97.2 | O54: 12.9 | P54: 11.6 | Q54: =IF(ROW()>=5,1,0) -> 1 | R54: =IF(AND(ROW()>=5,ROW()+3<=339),1,0) -> 1 | S54: =IF(AND(ROW()>=5,ROW()+6<=339),1,0) -> 1 | T54: =IF(AND(ROW()>=5,ROW()+12<=339),1,0) -> 1
A55: 2002-06 | B55: 24.08 | C55: 8.2767 | D55: =B55*C55 -> 199.30294 | E55: =100*LN(B55/B54) -> -5.139711 | F55: =100*LN(C55/C54) -> -0.0036245673 | G55: =100*LN(D55/D54) -> -5.1433355 | H55: 100.1 | I55: 97.5 | J55: 99.2 | K55: =H55-H54 -> -0.2 | L55: =I55-I54 -> 0.1 | M55: =J55-J54 -> 0.3 | N55: 97.2 | O55: 12.4 | P55: 11.7 | Q55: =IF(ROW()>=5,1,0) -> 1 | R55: =IF(AND(ROW()>=5,ROW()+3<=339),1,0) -> 1 | S55: =IF(AND(ROW()>=5,ROW()+6<=339),1,0) -> 1 | T55: =IF(AND(ROW()>=5,ROW()+12<=339),1,0) -> 1
A56: 2002-07 | B56: 25.74 | C56: 8.2768 | D56: =B56*C56 -> 213.04483 | E56: =100*LN(B56/B55) -> 6.6664582 | F56: =100*LN(C56/C55) -> 0.0012082037 | G56: =100*LN(D56/D55) -> 6.6676664 | H56: 99.8 | I56: 97.7 | J56: 99.1 | K56: =H56-H55 -> -0.3 | L56: =I56-I55 -> 0.2 | M56: =J56-J55 -> -0.1 | N56: 97.5 | O56: 12.8 | P56: 11.8 | Q56: =IF(ROW()>=5,1,0) -> 1 | R56: =IF(AND(ROW()>=5,ROW()+3<=339),1,0) -> 1 | S56: =IF(AND(ROW()>=5,ROW()+6<=339),1,0) -> 1 | T56: =IF(AND(ROW()>=5,ROW()+12<=339),1,0) -> 1
A57: 2002-08 | B57: 26.65 | C57: 8.2767 | D57: =B57*C57 -> 220.57405 | E57: =100*LN(B57/B56) -> 3.4742948 | F57: =100*LN(C57/C56) -> -0.0012082037 | G57: =100*LN(D57/D56) -> 3.4730866 | H57: 100.7 | I57: 98.3 | J57: 99.3 | K57: =H57-H56 -> 0.9 | L57: =I57-I56 -> 0.6 | M57: =J57-J56 -> 0.2 | N57: 98 | O57: 12.7 | P57: 12 | Q57: =IF(ROW()>=5,1,0) -> 1 | R57: =IF(AND(ROW()>=5,ROW()+3<=339),1,0) -> 1 | S57: =IF(AND(ROW()>=5,ROW()+6<=339),1,0) -> 1 | T57: =IF(AND(ROW()>=5,ROW()+12<=339),1,0) -> 1
A58: 2002-09 | B58: 28.4 | C58: 8.277 | D58: =B58*C58 -> 235.0668 | E58: =100*LN(B58/B57) -> 6.3599995 | F58: =100*LN(C58/C57) -> 0.0036245673 | G58: =100*LN(D58/D57) -> 6.363624 | H58: 101.8 | I58: 98.6 | J58: 99.3 | K58: =H58-H57 -> 1.1 | L58: =I58-I57 -> 0.3 | M58: =J58-J57 -> 0 | N58: 98.8 | O58: 13.8 | P58: 12.2 | Q58: =IF(ROW()>=5,1,0) -> 1 | R58: =IF(AND(ROW()>=5,ROW()+3<=339),1,0) -> 1 | S58: =IF(AND(ROW()>=5,ROW()+6<=339),1,0) -> 1 | T58: =IF(AND(ROW()>=5,ROW()+12<=339),1,0) -> 1
A59: 2002-10 | B59: 27.54 | C59: 8.2772 | D59: =B59*C59 -> 227.95409 | E59: =100*LN(B59/B58) -> -3.0749652 | F59: =100*LN(C59/C58) -> 0.0024163052 | G59: =100*LN(D59/D58) -> -3.0725489 | H59: 102.6 | I59: 99 | J59: 99.2 | K59: =H59-H58 -> 0.8 | L59: =I59-I58 -> 0.4 | M59: =J59-J58 -> -0.1 | N59: 99.4 | O59: 14.2 | P59: 12.3 | Q59: =IF(ROW()>=5,1,0) -> 1 | R59: =IF(AND(ROW()>=5,ROW()+3<=339),1,0) -> 1 | S59: =IF(AND(ROW()>=5,ROW()+6<=339),1,0) -> 1 | T59: =IF(AND(ROW()>=5,ROW()+12<=339),1,0) -> 1
A60: 2002-11 | B60: 24.34 | C60: 8.2772 | D60: =B60*C60 -> 201.46705 | E60: =100*LN(B60/B59) -> -12.351841 | F60: =100*LN(C60/C59) -> 0 | G60: =100*LN(D60/D59) -> -12.351841 | H60: 105.7 | I60: 99.6 | J60: 99.3 | K60: =H60-H59 -> 3.1 | L60: =I60-I59 -> 0.6 | M60: =J60-J59 -> 0.1 | N60: 100.5 | O60: 14.5 | P60: 12.4 | Q60: =IF(ROW()>=5,1,0) -> 1 | R60: =IF(AND(ROW()>=5,ROW()+3<=339),1,0) -> 1 | S60: =IF(AND(ROW()>=5,ROW()+6<=339),1,0) -> 1 | T60: =IF(AND(ROW()>=5,ROW()+12<=339),1,0) -> 1
A61: 2002-12 | B61: 28.33 | C61: 8.2777 | D61: =B61*C61 -> 234.50724 | E61: =100*LN(B61/B60) -> 15.180023 | F61: =100*LN(C61/C60) -> 0.0060405076 | G61: =100*LN(D61/D60) -> 15.186063 | H61: 107.2 | I61: 100.4 | J61: 99.6 | K61: =H61-H60 -> 1.5 | L61: =I61-I60 -> 0.8 | M61: =J61-J60 -> 0.3 | N61: 101.3 | O61: 14.9 | P61: 12.6 | Q61: =IF(ROW()>=5,1,0) -> 1 | R61: =IF(AND(ROW()>=5,ROW()+3<=339),1,0) -> 1 | S61: =IF(AND(ROW()>=5,ROW()+6<=339),1,0) -> 1 | T61: =IF(AND(ROW()>=5,ROW()+12<=339),1,0) -> 1
A62: 2003-01 | B62: 31.18 | C62: 8.2775 | D62: =B62*C62 -> 258.09245 | E62: =100*LN(B62/B61) -> 9.585555 | F62: =100*LN(C62/C61) -> -0.0024161593 | G62: =100*LN(D62/D61) -> 9.5831388 | H62: 110.2 | I62: 102.4 | J62: 100.4 | K62: =H62-H61 -> 3 | L62: =I62-I61 -> 2 | M62: =J62-J61 -> 0.8 | N62: 103.2 | Q62: =IF(ROW()>=5,1,0) -> 1 | R62: =IF(AND(ROW()>=5,ROW()+3<=339),1,0) -> 1 | S62: =IF(AND(ROW()>=5,ROW()+6<=339),1,0) -> 1 | T62: =IF(AND(ROW()>=5,ROW()+12<=339),1,0) -> 1
A63: 2003-02 | B63: 32.77 | C63: 8.278 | D63: =B63*C63 -> 271.27006 | E63: =100*LN(B63/B62) -> 4.9736599 | F63: =100*LN(C63/C62) -> 0.0060402887 | G63: =100*LN(D63/D62) -> 4.9797002 | H63: 113.4 | I63: 104 | J63: 100.2 | K63: =H63-H62 -> 3.2 | L63: =I63-I62 -> 1.6 | M63: =J63-J62 -> -0.2 | N63: 104.8 | O63: 19.8 | P63: 17.5 | Q63: =IF(ROW()>=5,1,0) -> 1 | R63: =IF(AND(ROW()>=5,ROW()+3<=339),1,0) -> 1 | S63: =IF(AND(ROW()>=5,ROW()+6<=339),1,0) -> 1 | T63: =IF(AND(ROW()>=5,ROW()+12<=339),1,0) -> 1
A64: 2003-03 | B64: 30.61 | C64: 8.2773 | D64: =B64*C64 -> 253.36815 | E64: =100*LN(B64/B63) -> -6.818671 | F64: =100*LN(C64/C63) -> -0.0084565064 | G64: =100*LN(D64/D63) -> -6.8271275 | H64: 114.4 | I64: 104.6 | J64: 100.9 | K64: =H64-H63 -> 1 | L64: =I64-I63 -> 0.6 | M64: =J64-J63 -> 0.7 | N64: 105.8 | O64: 16.9 | P64: 17.2 | Q64: =IF(ROW()>=5,1,0) -> 1 | R64: =IF(AND(ROW()>=5,ROW()+3<=339),1,0) -> 1 | S64: =IF(AND(ROW()>=5,ROW()+6<=339),1,0) -> 1 | T64: =IF(AND(ROW()>=5,ROW()+12<=339),1,0) -> 1
A65: 2003-04 | B65: 25 | C65: 8.2772 | D65: =B65*C65 -> 206.93 | E65: =100*LN(B65/B64) -> -20.245093 | F65: =100*LN(C65/C64) -> -0.0012081307 | G65: =100*LN(D65/D64) -> -20.246301 | H65: 112.6 | I65: 103.6 | J65: 101 | K65: =H65-H64 -> -1.8 | L65: =I65-I64 -> -1 | M65: =J65-J64 -> 0.1 | N65: 105.9 | O65: 14.9 | P65: 16.4 | Q65: =IF(ROW()>=5,1,0) -> 1 | R65: =IF(AND(ROW()>=5,ROW()+3<=339),1,0) -> 1 | S65: =IF(AND(ROW()>=5,ROW()+6<=339),1,0) -> 1 | T65: =IF(AND(ROW()>=5,ROW()+12<=339),1,0) -> 1
A66: 2003-05 | B66: 25.86 | C66: 8.2769 | D66: =B66*C66 -> 214.04063 | E66: =100*LN(B66/B65) -> 3.3821548 | F66: =100*LN(C66/C65) -> -0.0036244797 | G66: =100*LN(D66/D65) -> 3.3785304 | H66: 107.5 | I66: 102 | J66: 100.7 | K66: =H66-H65 -> -5.1 | L66: =I66-I65 -> -1.6 | M66: =J66-J65 -> -0.3 | N66: 104.4 | O66: 13.7 | P66: 15.9 | Q66: =IF(ROW()>=5,1,0) -> 1 | R66: =IF(AND(ROW()>=5,ROW()+3<=339),1,0) -> 1 | S66: =IF(AND(ROW()>=5,ROW()+6<=339),1,0) -> 1 | T66: =IF(AND(ROW()>=5,ROW()+12<=339),1,0) -> 1
A67: 2003-06 | B67: 27.65 | C67: 8.2771 | D67: =B67*C67 -> 228.86182 | E67: =100*LN(B67/B66) -> 6.6928355 | F67: =100*LN(C67/C66) -> 0.0024163344 | G67: =100*LN(D67/D66) -> 6.6952518 | H67: 105.2 | I67: 101.3 | J67: 100.3 | K67: =H67-H66 -> -2.3 | L67: =I67-I66 -> -0.7 | M67: =J67-J66 -> -0.4 | N67: 103.9 | O67: 16.9 | P67: 16.2 | Q67: =IF(ROW()>=5,1,0) -> 1 | R67: =IF(AND(ROW()>=5,ROW()+3<=339),1,0) -> 1 | S67: =IF(AND(ROW()>=5,ROW()+6<=339),1,0) -> 1 | T67: =IF(AND(ROW()>=5,ROW()+12<=339),1,0) -> 1
A68: 2003-07 | B68: 28.35 | C68: 8.2773 | D68: =B68*C68 -> 234.66145 | E68: =100*LN(B68/B67) -> 2.5001302 | F68: =100*LN(C68/C67) -> 0.002416276 | G68: =100*LN(D68/D67) -> 2.5025465 | H68: 105 | I68: 101.4 | J68: 100.5 | K68: =H68-H67 -> -0.2 | L68: =I68-I67 -> 0.1 | M68: =J68-J67 -> 0.2 | N68: 104 | O68: 16.5 | P68: 16.4 | Q68: =IF(ROW()>=5,1,0) -> 1 | R68: =IF(AND(ROW()>=5,ROW()+3<=339),1,0) -> 1 | S68: =IF(AND(ROW()>=5,ROW()+6<=339),1,0) -> 1 | T68: =IF(AND(ROW()>=5,ROW()+12<=339),1,0) -> 1
A69: 2003-08 | B69: 29.89 | C69: 8.277 | D69: =B69*C69 -> 247.39953 | E69: =100*LN(B69/B68) -> 5.2896946 | F69: =100*LN(C69/C68) -> -0.0036244359 | G69: =100*LN(D69/D68) -> 5.2860702 | H69: 104.6 | I69: 101.4 | J69: 100.9 | K69: =H69-H68 -> -0.4 | L69: =I69-I68 -> 0 | M69: =J69-J68 -> 0.4 | N69: 104 | O69: 17.1 | P69: 16.5 | Q69: =IF(ROW()>=5,1,0) -> 1 | R69: =IF(AND(ROW()>=5,ROW()+3<=339),1,0) -> 1 | S69: =IF(AND(ROW()>=5,ROW()+6<=339),1,0) -> 1 | T69: =IF(AND(ROW()>=5,ROW()+12<=339),1,0) -> 1
A70: 2003-09 | B70: 27.11 | C70: 8.2772 | D70: =B70*C70 -> 224.39489 | E70: =100*LN(B70/B69) -> -9.7621313 | F70: =100*LN(C70/C69) -> 0.0024163052 | G70: =100*LN(D70/D69) -> -9.759715 | H70: 104.5 | I70: 101.4 | J70: 101.1 | K70: =H70-H69 -> -0.1 | L70: =I70-I69 -> 0 | M70: =J70-J69 -> 0.2 | N70: 104.1 | O70: 16.3 | P70: 16.5 | Q70: =IF(ROW()>=5,1,0) -> 1 | R70: =IF(AND(ROW()>=5,ROW()+3<=339),1,0) -> 1 | S70: =IF(AND(ROW()>=5,ROW()+6<=339),1,0) -> 1 | T70: =IF(AND(ROW()>=5,ROW()+12<=339),1,0) -> 1
A71: 2003-10 | B71: 29.61 | C71: 8.2768 | D71: =B71*C71 -> 245.07605 | E71: =100*LN(B71/B70) -> 8.8209479 | F71: =100*LN(C71/C70) -> -0.0048326688 | G71: =100*LN(D71/D70) -> 8.8161152 | H71: 103.9 | I71: 101.2 | J71: 101.8 | K71: =H71-H70 -> -0.6 | L71: =I71-I70 -> -0.2 | M71: =J71-J70 -> 0.7 | N71: 104.6 | O71: 17.2 | P71: 16.7 | Q71: =IF(ROW()>=5,1,0) -> 1 | R71: =IF(AND(ROW()>=5,ROW()+3<=339),1,0) -> 1 | S71: =IF(AND(ROW()>=5,ROW()+6<=339),1,0) -> 1 | T71: =IF(AND(ROW()>=5,ROW()+12<=339),1,0) -> 1
A72: 2003-11 | B72: 28.75 | C72: 8.2769 | D72: =B72*C72 -> 237.96087 | E72: =100*LN(B72/B71) -> -2.9474375 | F72: =100*LN(C72/C71) -> 0.0012081891 | G72: =100*LN(D72/D71) -> -2.9462293 | H72: 103 | I72: 101.9 | J72: 103 | K72: =H72-H71 -> -0.9 | L72: =I72-I71 -> 0.7 | M72: =J72-J71 -> 1.2 | N72: 105.9 | O72: 17.9 | P72: 16.8 | Q72: =IF(ROW()>=5,1,0) -> 1 | R72: =IF(AND(ROW()>=5,ROW()+3<=339),1,0) -> 1 | S72: =IF(AND(ROW()>=5,ROW()+6<=339),1,0) -> 1 | T72: =IF(AND(ROW()>=5,ROW()+12<=339),1,0) -> 1
A73: 2003-12 | B73: 29.81 | C73: 8.277 | D73: =B73*C73 -> 246.73737 | E73: =100*LN(B73/B72) -> 3.620614 | F73: =100*LN(C73/C72) -> 0.0012081745 | G73: =100*LN(D73/D72) -> 3.6218222 | H73: 104.7 | I73: 103 | J73: 103.2 | K73: =H73-H72 -> 1.7 | L73: =I73-I72 -> 1.1 | M73: =J73-J72 -> 0.2 | N73: 107.1 | O73: 18.1 | P73: 17 | Q73: =IF(ROW()>=5,1,0) -> 1 | R73: =IF(AND(ROW()>=5,ROW()+3<=339),1,0) -> 1 | S73: =IF(AND(ROW()>=5,ROW()+6<=339),1,0) -> 1 | T73: =IF(AND(ROW()>=5,ROW()+12<=339),1,0) -> 1
A74: 2004-01 | B74: 31.28 | C74: 8.277 | D74: =B74*C74 -> 258.90456 | E74: =100*LN(B74/B73) -> 4.8135008 | F74: =100*LN(C74/C73) -> 0 | G74: =100*LN(D74/D73) -> 4.8135008 | H74: 104.1 | I74: 103.5 | J74: 103.2 | K74: =H74-H73 -> -0.6 | L74: =I74-I73 -> 0.5 | M74: =J74-J73 -> 0 | N74: 107.4 | Q74: =IF(ROW()>=5,1,0) -> 1 | R74: =IF(AND(ROW()>=5,ROW()+3<=339),1,0) -> 1 | S74: =IF(AND(ROW()>=5,ROW()+6<=339),1,0) -> 1 | T74: =IF(AND(ROW()>=5,ROW()+12<=339),1,0) -> 1
A75: 2004-02 | B75: 30.86 | C75: 8.2771 | D75: =B75*C75 -> 255.43131 | E75: =100*LN(B75/B74) -> -1.3518069 | F75: =100*LN(C75/C74) -> 0.0012081599 | G75: =100*LN(D75/D74) -> -1.3505987 | H75: 102.9 | I75: 103.5 | J75: 102.1 | K75: =H75-H74 -> -1.2 | L75: =I75-I74 -> 0 | M75: =J75-J74 -> -1.1 | N75: 108.1 | O75: 23.2 | P75: 16.6 | Q75: =IF(ROW()>=5,1,0) -> 1 | R75: =IF(AND(ROW()>=5,ROW()+3<=339),1,0) -> 1 | S75: =IF(AND(ROW()>=5,ROW()+6<=339),1,0) -> 1 | T75: =IF(AND(ROW()>=5,ROW()+12<=339),1,0) -> 1
A76: 2004-03 | B76: 33.63 | C76: 8.2771 | D76: =B76*C76 -> 278.35887 | E76: =100*LN(B76/B75) -> 8.5957679 | F76: =100*LN(C76/C75) -> 0 | G76: =100*LN(D76/D75) -> 8.5957679 | H76: 102.8 | I76: 104 | J76: 103 | K76: =H76-H75 -> -0.1 | L76: =I76-I75 -> 0.5 | M76: =J76-J75 -> 0.9 | N76: 109.5 | O76: 19.4 | P76: 17.7 | Q76: =IF(ROW()>=5,1,0) -> 1 | R76: =IF(AND(ROW()>=5,ROW()+3<=339),1,0) -> 1 | S76: =IF(AND(ROW()>=5,ROW()+6<=339),1,0) -> 1 | T76: =IF(AND(ROW()>=5,ROW()+12<=339),1,0) -> 1
A77: 2004-04 | B77: 33.59 | C77: 8.2769 | D77: =B77*C77 -> 278.02107 | E77: =100*LN(B77/B76) -> -0.11901221 | F77: =100*LN(C77/C76) -> -0.0024163344 | G77: =100*LN(D77/D76) -> -0.12142855 | H77: 104.2 | I77: 105 | J77: 103.8 | K77: =H77-H76 -> 1.4 | L77: =I77-I76 -> 1 | M77: =J77-J76 -> 0.8 | N77: 110.5 | O77: 19.1 | P77: 18.2 | Q77: =IF(ROW()>=5,1,0) -> 1 | R77: =IF(AND(ROW()>=5,ROW()+3<=339),1,0) -> 1 | S77: =IF(AND(ROW()>=5,ROW()+6<=339),1,0) -> 1 | T77: =IF(AND(ROW()>=5,ROW()+12<=339),1,0) -> 1
A78: 2004-05 | B78: 37.57 | C78: 8.2771 | D78: =B78*C78 -> 310.97065 | E78: =100*LN(B78/B77) -> 11.197746 | F78: =100*LN(C78/C77) -> 0.0024163344 | G78: =100*LN(D78/D77) -> 11.200162 | H78: 106 | I78: 105.7 | J78: 104.4 | K78: =H78-H77 -> 1.8 | L78: =I78-I77 -> 0.7 | M78: =J78-J77 -> 0.6 | N78: 111.2 | O78: 17.5 | P78: 18.1 | Q78: =IF(ROW()>=5,1,0) -> 1 | R78: =IF(AND(ROW()>=5,ROW()+3<=339),1,0) -> 1 | S78: =IF(AND(ROW()>=5,ROW()+6<=339),1,0) -> 1 | T78: =IF(AND(ROW()>=5,ROW()+12<=339),1,0) -> 1
A79: 2004-06 | B79: 35.18 | C79: 8.2767 | D79: =B79*C79 -> 291.17431 | E79: =100*LN(B79/B78) -> -6.572812 | F79: =100*LN(C79/C78) -> -0.0048327272 | G79: =100*LN(D79/D78) -> -6.5776448 | H79: 109.4 | I79: 106.4 | J79: 105 | K79: =H79-H78 -> 3.4 | L79: =I79-I78 -> 0.7 | M79: =J79-J78 -> 0.6 | N79: 111.8 | O79: 16.2 | P79: 17.7 | Q79: =IF(ROW()>=5,1,0) -> 1 | R79: =IF(AND(ROW()>=5,ROW()+3<=339),1,0) -> 1 | S79: =IF(AND(ROW()>=5,ROW()+6<=339),1,0) -> 1 | T79: =IF(AND(ROW()>=5,ROW()+12<=339),1,0) -> 1
A80: 2004-07 | B80: 38.22 | C80: 8.2767 | D80: =B80*C80 -> 316.33547 | E80: =100*LN(B80/B79) -> 8.28812 | F80: =100*LN(C80/C79) -> 0 | G80: =100*LN(D80/D79) -> 8.28812 | H80: 111 | I80: 106.4 | J80: 105.3 | K80: =H80-H79 -> 1.6 | L80: =I80-I79 -> 0 | M80: =J80-J79 -> 0.3 | N80: 112 | O80: 15.5 | P80: 17.3 | Q80: =IF(ROW()>=5,1,0) -> 1 | R80: =IF(AND(ROW()>=5,ROW()+3<=339),1,0) -> 1 | S80: =IF(AND(ROW()>=5,ROW()+6<=339),1,0) -> 1 | T80: =IF(AND(ROW()>=5,ROW()+12<=339),1,0) -> 1
A81: 2004-08 | B81: 42.74 | C81: 8.2768 | D81: =B81*C81 -> 353.75043 | E81: =100*LN(B81/B80) -> 11.177631 | F81: =100*LN(C81/C80) -> 0.0012082037 | G81: =100*LN(D81/D80) -> 11.178839 | H81: 111.9 | I81: 106.8 | J81: 105.3 | K81: =H81-H80 -> 0.9 | L81: =I81-I80 -> 0.4 | M81: =J81-J80 -> 0 | N81: 112.9 | O81: 15.9 | P81: 17.1 | Q81: =IF(ROW()>=5,1,0) -> 1 | R81: =IF(AND(ROW()>=5,ROW()+3<=339),1,0) -> 1 | S81: =IF(AND(ROW()>=5,ROW()+6<=339),1,0) -> 1 | T81: =IF(AND(ROW()>=5,ROW()+12<=339),1,0) -> 1
A82: 2004-09 | B82: 43.2 | C82: 8.2767 | D82: =B82*C82 -> 357.55344 | E82: =100*LN(B82/B81) -> 1.0705245 | F82: =100*LN(C82/C81) -> -0.0012082037 | G82: =100*LN(D82/D81) -> 1.0693163 | H82: 114 | I82: 108 | J82: 105.2 | K82: =H82-H81 -> 2.1 | L82: =I82-I81 -> 1.2 | M82: =J82-J81 -> -0.1 | N82: 113.7 | O82: 16.1 | P82: 17 | Q82: =IF(ROW()>=5,1,0) -> 1 | R82: =IF(AND(ROW()>=5,ROW()+3<=339),1,0) -> 1 | S82: =IF(AND(ROW()>=5,ROW()+6<=339),1,0) -> 1 | T82: =IF(AND(ROW()>=5,ROW()+12<=339),1,0) -> 1
A83: 2004-10 | B83: 49.78 | C83: 8.2765 | D83: =B83*C83 -> 412.00417 | E83: =100*LN(B83/B82) -> 14.17728 | F83: =100*LN(C83/C82) -> -0.0024164512 | G83: =100*LN(D83/D82) -> 14.174864 | H83: 116.7 | I83: 108.4 | J83: 104.3 | K83: =H83-H82 -> 2.7 | L83: =I83-I82 -> 0.4 | M83: =J83-J82 -> -0.9 | N83: 114.2 | O83: 15.7 | P83: 16.9 | Q83: =IF(ROW()>=5,1,0) -> 1 | R83: =IF(AND(ROW()>=5,ROW()+3<=339),1,0) -> 1 | S83: =IF(AND(ROW()>=5,ROW()+6<=339),1,0) -> 1 | T83: =IF(AND(ROW()>=5,ROW()+12<=339),1,0) -> 1
A84: 2004-11 | B84: 43.11 | C84: 8.2765 | D84: =B84*C84 -> 356.79991 | E84: =100*LN(B84/B83) -> -14.385831 | F84: =100*LN(C84/C83) -> 0 | G84: =100*LN(D84/D83) -> -14.385831 | H84: 118.3 | I84: 108.1 | J84: 102.8 | K84: =H84-H83 -> 1.6 | L84: =I84-I83 -> -0.3 | M84: =J84-J83 -> -1.5 | N84: 113.7 | O84: 14.8 | P84: 16.8 | Q84: =IF(ROW()>=5,1,0) -> 1 | R84: =IF(AND(ROW()>=5,ROW()+3<=339),1,0) -> 1 | S84: =IF(AND(ROW()>=5,ROW()+6<=339),1,0) -> 1 | T84: =IF(AND(ROW()>=5,ROW()+12<=339),1,0) -> 1
A85: 2004-12 | B85: 39.6 | C85: 8.2765 | D85: =B85*C85 -> 327.7494 | E85: =100*LN(B85/B84) -> -8.492587 | F85: =100*LN(C85/C84) -> 0 | G85: =100*LN(D85/D84) -> -8.492587 | H85: 115 | I85: 107.1 | J85: 102.4 | K85: =H85-H84 -> -3.3 | L85: =I85-I84 -> -1 | M85: =J85-J84 -> -0.4 | N85: 112 | O85: 14.4 | P85: 16.7 | Q85: =IF(ROW()>=5,1,0) -> 1 | R85: =IF(AND(ROW()>=5,ROW()+3<=339),1,0) -> 1 | S85: =IF(AND(ROW()>=5,ROW()+6<=339),1,0) -> 1 | T85: =IF(AND(ROW()>=5,ROW()+12<=339),1,0) -> 1
A86: 2005-01 | B86: 44.51 | C86: 8.2765 | D86: =B86*C86 -> 368.38702 | E86: =100*LN(B86/B85) -> 11.688476 | F86: =100*LN(C86/C85) -> 0 | G86: =100*LN(D86/D85) -> 11.688476 | H86: 112.6 | I86: 105.8 | J86: 101.9 | K86: =H86-H85 -> -2.4 | L86: =I86-I85 -> -1.3 | M86: =J86-J85 -> -0.5 | N86: 110.7 | Q86: =IF(ROW()>=5,1,0) -> 1 | R86: =IF(AND(ROW()>=5,ROW()+3<=339),1,0) -> 1 | S86: =IF(AND(ROW()>=5,ROW()+6<=339),1,0) -> 1 | T86: =IF(AND(ROW()>=5,ROW()+12<=339),1,0) -> 1
A87: 2005-02 | B87: 45.48 | C87: 8.2765 | D87: =B87*C87 -> 376.41522 | E87: =100*LN(B87/B86) -> 2.1558786 | F87: =100*LN(C87/C86) -> 0 | G87: =100*LN(D87/D86) -> 2.1558786 | H87: 113.1 | I87: 105.4 | J87: 103.9 | K87: =H87-H86 -> 0.5 | L87: =I87-I86 -> -0.4 | M87: =J87-J86 -> 2 | N87: 109.8 | O87: 7.6 | P87: 16.9 | Q87: =IF(ROW()>=5,1,0) -> 1 | R87: =IF(AND(ROW()>=5,ROW()+3<=339),1,0) -> 1 | S87: =IF(AND(ROW()>=5,ROW()+6<=339),1,0) -> 1 | T87: =IF(AND(ROW()>=5,ROW()+12<=339),1,0) -> 1
A88: 2005-03 | B88: 53.1 | C88: 8.2765 | D88: =B88*C88 -> 439.48215 | E88: =100*LN(B88/B87) -> 15.490426 | F88: =100*LN(C88/C87) -> 0 | G88: =100*LN(D88/D87) -> 15.490426 | H88: 115.5 | I88: 105.6 | J88: 102.7 | K88: =H88-H87 -> 2.4 | L88: =I88-I87 -> 0.2 | M88: =J88-J87 -> -1.2 | N88: 109.7 | O88: 15.1 | P88: 16.2 | Q88: =IF(ROW()>=5,1,0) -> 1 | R88: =IF(AND(ROW()>=5,ROW()+3<=339),1,0) -> 1 | S88: =IF(AND(ROW()>=5,ROW()+6<=339),1,0) -> 1 | T88: =IF(AND(ROW()>=5,ROW()+12<=339),1,0) -> 1
A89: 2005-04 | B89: 51.88 | C89: 8.2765 | D89: =B89*C89 -> 429.38482 | E89: =100*LN(B89/B88) -> -2.3243569 | F89: =100*LN(C89/C88) -> 0 | G89: =100*LN(D89/D88) -> -2.3243569 | H89: 117.6 | I89: 105.8 | J89: 101.8 | K89: =H89-H88 -> 2.1 | L89: =I89-I88 -> 0.2 | M89: =J89-J88 -> -0.9 | N89: 109.9 | O89: 16 | P89: 16.2 | Q89: =IF(ROW()>=5,1,0) -> 1 | R89: =IF(AND(ROW()>=5,ROW()+3<=339),1,0) -> 1 | S89: =IF(AND(ROW()>=5,ROW()+6<=339),1,0) -> 1 | T89: =IF(AND(ROW()>=5,ROW()+12<=339),1,0) -> 1
A90: 2005-05 | B90: 48.65 | C90: 8.2765 | D90: =B90*C90 -> 402.65172 | E90: =100*LN(B90/B89) -> -6.4281551 | F90: =100*LN(C90/C89) -> 0 | G90: =100*LN(D90/D89) -> -6.4281551 | H90: 118.9 | I90: 106 | J90: 101.8 | K90: =H90-H89 -> 1.3 | L90: =I90-I89 -> 0.2 | M90: =J90-J89 -> 0 | N90: 110 | O90: 16.6 | P90: 16.3 | Q90: =IF(ROW()>=5,1,0) -> 1 | R90: =IF(AND(ROW()>=5,ROW()+3<=339),1,0) -> 1 | S90: =IF(AND(ROW()>=5,ROW()+6<=339),1,0) -> 1 | T90: =IF(AND(ROW()>=5,ROW()+12<=339),1,0) -> 1
A91: 2005-06 | B91: 54.35 | C91: 8.2765 | D91: =B91*C91 -> 449.82777 | E91: =100*LN(B91/B90) -> 11.07928 | F91: =100*LN(C91/C90) -> 0 | G91: =100*LN(D91/D90) -> 11.07928 | H91: 116.2 | I91: 105.2 | J91: 101.6 | K91: =H91-H90 -> -2.7 | L91: =I91-I90 -> -0.8 | M91: =J91-J90 -> -0.2 | N91: 109 | O91: 16.8 | P91: 16.4 | Q91: =IF(ROW()>=5,1,0) -> 1 | R91: =IF(AND(ROW()>=5,ROW()+3<=339),1,0) -> 1 | S91: =IF(AND(ROW()>=5,ROW()+6<=339),1,0) -> 1 | T91: =IF(AND(ROW()>=5,ROW()+12<=339),1,0) -> 1
A92: 2005-07 | B92: 57.52 | C92: 8.2264 | D92: =B92*C92 -> 473.18253 | E92: =100*LN(B92/B91) -> 5.66881 | F92: =100*LN(C92/C91) -> -0.60716788 | G92: =100*LN(D92/D91) -> 5.0616421 | H92: 115.6 | I92: 105.2 | J92: 101.8 | K92: =H92-H91 -> -0.6 | L92: =I92-I91 -> 0 | M92: =J92-J91 -> 0.2 | N92: 108.5 | O92: 16.1 | P92: 16.3 | Q92: =IF(ROW()>=5,1,0) -> 1 | R92: =IF(AND(ROW()>=5,ROW()+3<=339),1,0) -> 1 | S92: =IF(AND(ROW()>=5,ROW()+6<=339),1,0) -> 1 | T92: =IF(AND(ROW()>=5,ROW()+12<=339),1,0) -> 1
A93: 2005-08 | B93: 63.98 | C93: 8.1017 | D93: =B93*C93 -> 518.34677 | E93: =100*LN(B93/B92) -> 10.643782 | F93: =100*LN(C93/C92) -> -1.5274579 | G93: =100*LN(D93/D92) -> 9.1163242 | H93: 116.4 | I93: 105.3 | J93: 101.3 | K93: =H93-H92 -> 0.8 | L93: =I93-I92 -> 0.1 | M93: =J93-J92 -> -0.5 | N93: 108.1 | O93: 16 | P93: 16.3 | Q93: =IF(ROW()>=5,1,0) -> 1 | R93: =IF(AND(ROW()>=5,ROW()+3<=339),1,0) -> 1 | S93: =IF(AND(ROW()>=5,ROW()+6<=339),1,0) -> 1 | T93: =IF(AND(ROW()>=5,ROW()+12<=339),1,0) -> 1
A94: 2005-09 | B94: 62.91 | C94: 8.0919 | D94: =B94*C94 -> 509.06143 | E94: =100*LN(B94/B93) -> -1.6865401 | F94: =100*LN(C94/C93) -> -0.12103549 | G94: =100*LN(D94/D93) -> -1.8075756 | H94: 115.8 | I94: 104.5 | J94: 100.9 | K94: =H94-H93 -> -0.6 | L94: =I94-I93 -> -0.8 | M94: =J94-J93 -> -0.4 | N94: 107.1 | O94: 16.5 | P94: 16.3 | Q94: =IF(ROW()>=5,1,0) -> 1 | R94: =IF(AND(ROW()>=5,ROW()+3<=339),1,0) -> 1 | S94: =IF(AND(ROW()>=5,ROW()+6<=339),1,0) -> 1 | T94: =IF(AND(ROW()>=5,ROW()+12<=339),1,0) -> 1
A95: 2005-10 | B95: 58.54 | C95: 8.0895 | D95: =B95*C95 -> 473.55933 | E95: =100*LN(B95/B94) -> -7.1994852 | F95: =100*LN(C95/C94) -> -0.029663688 | G95: =100*LN(D95/D94) -> -7.2291489 | H95: 114.9 | I95: 104 | J95: 101.2 | K95: =H95-H94 -> -0.9 | L95: =I95-I94 -> -0.5 | M95: =J95-J94 -> 0.3 | N95: 106.5 | O95: 16.1 | P95: 16.3 | Q95: =IF(ROW()>=5,1,0) -> 1 | R95: =IF(AND(ROW()>=5,ROW()+3<=339),1,0) -> 1 | S95: =IF(AND(ROW()>=5,ROW()+6<=339),1,0) -> 1 | T95: =IF(AND(ROW()>=5,ROW()+12<=339),1,0) -> 1
A96: 2005-11 | B96: 55.24 | C96: 8.084 | D96: =B96*C96 -> 446.56016 | E96: =100*LN(B96/B95) -> -5.8022953 | F96: =100*LN(C96/C95) -> -0.068012492 | G96: =100*LN(D96/D95) -> -5.8703078 | H96: 112 | I96: 103.2 | J96: 101.3 | K96: =H96-H95 -> -2.9 | L96: =I96-I95 -> -0.8 | M96: =J96-J95 -> 0.1 | N96: 105.4 | O96: 16.6 | P96: 16.4 | Q96: =IF(ROW()>=5,1,0) -> 1 | R96: =IF(AND(ROW()>=5,ROW()+3<=339),1,0) -> 1 | S96: =IF(AND(ROW()>=5,ROW()+6<=339),1,0) -> 1 | T96: =IF(AND(ROW()>=5,ROW()+12<=339),1,0) -> 1
A97: 2005-12 | B97: 56.86 | C97: 8.0755 | D97: =B97*C97 -> 459.17293 | E97: =100*LN(B97/B96) -> 2.8904778 | F97: =100*LN(C97/C96) -> -0.10520128 | G97: =100*LN(D97/D96) -> 2.7852765 | H97: 111.8 | I97: 103.2 | J97: 101.6 | K97: =H97-H96 -> -0.2 | L97: =I97-I96 -> 0 | M97: =J97-J96 -> 0.3 | N97: 105 | O97: 16.5 | P97: 16.4 | Q97: =IF(ROW()>=5,1,0) -> 1 | R97: =IF(AND(ROW()>=5,ROW()+3<=339),1,0) -> 1 | S97: =IF(AND(ROW()>=5,ROW()+6<=339),1,0) -> 1 | T97: =IF(AND(ROW()>=5,ROW()+12<=339),1,0) -> 1
A98: 2006-01 | B98: 62.99 | C98: 8.0654 | D98: =B98*C98 -> 508.03955 | E98: =100*LN(B98/B97) -> 10.238388 | F98: =100*LN(C98/C97) -> -0.12514793 | G98: =100*LN(D98/D97) -> 10.11324 | H98: 117.9 | I98: 103.1 | J98: 101.9 | K98: =H98-H97 -> 6.1 | L98: =I98-I97 -> -0.1 | M98: =J98-J97 -> 0.3 | N98: 106.5 | Q98: =IF(ROW()>=5,1,0) -> 1 | R98: =IF(AND(ROW()>=5,ROW()+3<=339),1,0) -> 1 | S98: =IF(AND(ROW()>=5,ROW()+6<=339),1,0) -> 1 | T98: =IF(AND(ROW()>=5,ROW()+12<=339),1,0) -> 1
A99: 2006-02 | B99: 60.21 | C99: 8.0512 | D99: =B99*C99 -> 484.76275 | E99: =100*LN(B99/B98) -> -4.5137532 | F99: =100*LN(C99/C98) -> -0.17621587 | G99: =100*LN(D99/D98) -> -4.6899691 | H99: 117.8 | I99: 103 | J99: 100.9 | K99: =H99-H98 -> -0.1 | L99: =I99-I98 -> -0.1 | M99: =J99-J98 -> -1 | N99: 106.8 | O99: 20.1 | P99: 16.2 | Q99: =IF(ROW()>=5,1,0) -> 1 | R99: =IF(AND(ROW()>=5,ROW()+3<=339),1,0) -> 1 | S99: =IF(AND(ROW()>=5,ROW()+6<=339),1,0) -> 1 | T99: =IF(AND(ROW()>=5,ROW()+12<=339),1,0) -> 1
A100: 2006-03 | B100: 62.06 | C100: 8.035 | D100: =B100*C100 -> 498.6521 | E100: =100*LN(B100/B99) -> 3.0263208 | F100: =100*LN(C100/C99) -> -0.20141495 | G100: =100*LN(D100/D99) -> 2.8249058 | H100: 116.7 | I100: 102.5 | J100: 100.8 | K100: =H100-H99 -> -1.1 | L100: =I100-I99 -> -0.5 | M100: =J100-J99 -> -0.1 | N100: 106.2 | O100: 17.8 | P100: 16.7 | Q100: =IF(ROW()>=5,1,0) -> 1 | R100: =IF(AND(ROW()>=5,ROW()+3<=339),1,0) -> 1 | S100: =IF(AND(ROW()>=5,ROW()+6<=339),1,0) -> 1 | T100: =IF(AND(ROW()>=5,ROW()+12<=339),1,0) -> 1
...

Sheet Customs_134
A1: month | B1: HS | C1: import_quantity_kg | D1: import_value_cny | E1: import_unit_value_cny_per_kg | F1: dlog_import_quantity | G1: dlog_import_unit_value | H1: dlog_oil_rmb | I1: link1_origin
A2: 2015-01 | B2: 27090000 | C2: 27978648204 | D2: 79981726350 | E2: =D2/C2 -> 2.8586701 | F2: ="" | G2: ="" | H2: =Monthly_338!G206 -> -26.16593 | I2: =IF(ROW()>=6,1,0) -> 0
A3: 2015-02 | B3: 27090000 | C3: 25557194316 | D3: 59902470834 | E3: =D3/C3 -> 2.3438594 | F3: =100*LN(C3/C2) -> -9.05228 | G3: =100*LN(E3/E2) -> -19.855763 | H3: =Monthly_338!G207 -> 20.138222 | I3: =IF(ROW()>=6,1,0) -> 0
A4: 2015-03 | B4: 27090000 | C4: 26809943375 | D4: 66890312271 | E4: =D4/C4 -> 2.4949815 | F4: =100*LN(C4/C3) -> 4.7853985 | G4: =100*LN(E4/E3) -> 6.2482409 | H4: =Monthly_338!G208 -> -4.0893815 | I4: =IF(ROW()>=6,1,0) -> 0
A5: 2015-04 | B5: 27090000 | C5: 30286800453 | D5: 75787075883 | E5: =D5/C5 -> 2.5023137 | F5: =100*LN(C5/C4) -> 12.193915 | G5: =100*LN(E5/E4) -> 0.29344789 | H5: =Monthly_338!G209 -> 5.6881688 | I5: =IF(ROW()>=6,1,0) -> 0
A6: 2015-05 | B6: 27090000 | C6: 23249324628 | D6: 61590313859 | E6: =D6/C6 -> 2.6491227 | F6: =100*LN(C6/C5) -> -26.443591 | G6: =100*LN(E6/E5) -> 5.7012746 | H6: =Monthly_338!G210 -> 7.4222992 | I6: =IF(ROW()>=6,1,0) -> 1
A7: 2015-06 | B7: 27090000 | C7: 29493441442 | D7: 81871167033 | E7: =D7/C7 -> 2.7759109 | F7: =100*LN(C7/C6) -> 23.789183 | G7: =100*LN(E7/E6) -> 4.6750431 | H7: =Monthly_338!G211 -> -4.1146383 | I7: =IF(ROW()>=6,1,0) -> 1
A8: 2015-07 | B8: 27090000 | C8: 30706239392 | D8: 84697996577 | E8: =D8/C8 -> 2.7583318 | F8: =100*LN(C8/C7) -> 4.0297957 | G8: =100*LN(E8/E7) -> -0.63528866 | H8: =Monthly_338!G212 -> -8.2878226 | I8: =IF(ROW()>=6,1,0) -> 1
A9: 2015-08 | B9: 27090000 | C9: 26587571237 | D9: 68739421967 | E9: =D9/C9 -> 2.5853968 | F9: =100*LN(C9/C8) -> -14.402201 | G9: =100*LN(E9/E8) -> -6.4747074 | H9: =Monthly_338!G213 -> -17.472842 | I9: =IF(ROW()>=6,1,0) -> 1
A10: 2015-09 | B10: 27090000 | C10: 27949501844 | D10: 65648379952 | E10: =D10/C10 -> 2.3488211 | F10: =100*LN(C10/C9) -> 4.9955516 | G10: =100*LN(E10/E9) -> -9.5965455 | H10: =Monthly_338!G214 -> 2.7982552 | I10: =IF(ROW()>=6,1,0) -> 1
A11: 2015-10 | B11: 27090000 | C11: 26352357942 | D11: 59420349169 | E11: =D11/C11 -> 2.2548399 | F11: =100*LN(C11/C10) -> -5.884162 | G11: =100*LN(E11/E10) -> -4.0834557 | H11: =Monthly_338!G215 -> 1.4177533 | I11: =IF(ROW()>=6,1,0) -> 1
A12: 2015-11 | B12: 27090000 | C12: 27340925460 | D12: 61147166049 | E12: =D12/C12 -> 2.2364702 | F12: =100*LN(C12/C11) -> 3.6826924 | G12: =100*LN(E12/E11) -> -0.81801538 | H12: =Monthly_338!G216 -> -8.7688649 | I12: =IF(ROW()>=6,1,0) -> 1
A13: 2015-12 | B13: 27090000 | C13: 33170862438 | D13: 66921003539 | E13: =D13/C13 -> 2.0174635 | F13: =100*LN(C13/C12) -> 19.328717 | G13: =100*LN(E13/E12) -> -10.305782 | H13: =Monthly_338!G217 -> -13.917449 | I13: =IF(ROW()>=6,1,0) -> 1
A14: 2016-01 | B14: 27090000 | C14: 26683027055 | D14: 48095137382 | E14: =D14/C14 -> 1.8024618 | F14: =100*LN(C14/C13) -> -21.764418 | G14: =100*LN(E14/E13) -> -11.268761 | H14: =Monthly_338!G218 -> -19.461772 | I14: =IF(ROW()>=6,1,0) -> 1
... A135: 2026-02 | B135: 27090000 | C135: 48045363286 | D135: 155487504853 | E135: =D135/C135 -> 3.2362645 | F135: =100*LN(C135/C134) -> -1.7399823 | G135: =100*LN(E135/E134) -> 1.3452502 | H135: =Monthly_338!G339 -> 5.337288 | I135: =IF(ROW()>=6,1,0) -> 1

Sheet Fig2_observations
A1: month | B1: variable | C1: value | D1: available | E1: primary_lp_origin_h0 | F1: primary_lp_origin_h12
A2: 1998-01 | B2: brent_usd_per_bbl | C2: 15.19 | D2: 1 | E2: 0 | F2: 0
A3: 1998-01 | B3: cny_per_usd | C3: 8.3094 | D3: 1 | E3: 0 | F3: 0
A4: 1998-01 | B4: oil_rmb_cny_per_bbl | C4: 126.21979 | D4: 1 | E4: 0 | F4: 0
A5: 1998-01 | B5: fuel_index_yoy | C5: 105.9 | D5: 1 | E5: 0 | F5: 0
A6: 1998-01 | B6: ppi_index_yoy | C6: 98.7 | D6: 1 | E6: 0 | F6: 0
A7: 1998-01 | B7: cpi_index_yoy | C7: 100.3 | D7: 1 | E7: 0 | F7: 0
A8: 1998-01 | B8: purchase_index_yoy | C8: 99.6 | D8: 1 | E8: 0 | F8: 0
A9: 1998-01 | B9: import_quantity_kg | D9: 0 | E9: 0 | F9: 0
A10: 1998-01 | B10: import_value_cny | D10: 0 | E10: 0 | F10: 0
A11: 1998-01 | B11: import_unit_value_cny_per_kg | D11: 0 | E11: 0 | F11: 0
A12: 1998-01 | B12: dlog_oil_rmb | D12: 0 | E12: 0 | F12: 0
A13: 1998-01 | B13: d_fuel_power_inflation | D13: 0 | E13: 0 | F13: 0
A14: 1998-01 | B14: d_ppi_inflation | D14: 0 | E14: 0 | F14: 0
A15: 1998-01 | B15: d_cpi_inflation | D15: 0 | E15: 0 | F15: 0
A16: 1998-01 | B16: dlog_import_unit_value | D16: 0 | E16: 0 | F16: 0
A17: 1998-02 | B17: brent_usd_per_bbl | C17: 14.07 | D17: 1 | E17: 0 | F17: 0
A18: 1998-02 | B18: cny_per_usd | C18: 8.3072 | D18: 1 | E18: 0 | F18: 0
A19: 1998-02 | B19: oil_rmb_cny_per_bbl | C19: 116.8823 | D19: 1 | E19: 0 | F19: 0
A20: 1998-02 | B20: fuel_index_yoy | C20: 101.5 | D20: 1 | E20: 0 | F20: 0
A21: 1998-02 | B21: ppi_index_yoy | C21: 97.4 | D21: 1 | E21: 0 | F21: 0
A22: 1998-02 | B22: cpi_index_yoy | C22: 99.9 | D22: 1 | E22: 0 | F22: 0
A23: 1998-02 | B23: purchase_index_yoy | C23: 98.3 | D23: 1 | E23: 0 | F23: 0
A24: 1998-02 | B24: import_quantity_kg | D24: 0 | E24: 0 | F24: 0
A25: 1998-02 | B25: import_value_cny | D25: 0 | E25: 0 | F25: 0
A26: 1998-02 | B26: import_unit_value_cny_per_kg | D26: 0 | E26: 0 | F26: 0
A27: 1998-02 | B27: dlog_oil_rmb | C27: -7.6857241 | D27: 1 | E27: 0 | F27: 0
A28: 1998-02 | B28: d_fuel_power_inflation | C28: -4.4 | D28: 1 | E28: 0 | F28: 0
A29: 1998-02 | B29: d_ppi_inflation | C29: -1.3 | D29: 1 | E29: 0 | F29: 0
A30: 1998-02 | B30: d_cpi_inflation | C30: -0.4 | D30: 1 | E30: 0 | F30: 0
A31: 1998-02 | B31: dlog_import_unit_value | D31: 0 | E31: 0 | F31: 0
A32: 1998-03 | B32: brent_usd_per_bbl | C32: 13.1 | D32: 1 | E32: 0 | F32: 0
A33: 1998-03 | B33: cny_per_usd | C33: 8.3076 | D33: 1 | E33: 0 | F33: 0
A34: 1998-03 | B34: oil_rmb_cny_per_bbl | C34: 108.82956 | D34: 1 | E34: 0 | F34: 0
A35: 1998-03 | B35: fuel_index_yoy | C35: 100.7 | D35: 1 | E35: 0 | F35: 0
A36: 1998-03 | B36: ppi_index_yoy | C36: 96.8 | D36: 1 | E36: 0 | F36: 0
A37: 1998-03 | B37: cpi_index_yoy | C37: 100.7 | D37: 1 | E37: 0 | F37: 0
A38: 1998-03 | B38: purchase_index_yoy | C38: 97.7 | D38: 1 | E38: 0 | F38: 0
A39: 1998-03 | B39: import_quantity_kg | D39: 0 | E39: 0 | F39: 0
A40: 1998-03 | B40: import_value_cny | D40: 0 | E40: 0 | F40: 0
A41: 1998-03 | B41: import_unit_value_cny_per_kg | D41: 0 | E41: 0 | F41: 0
A42: 1998-03 | B42: dlog_oil_rmb | C42: -7.1384491 | D42: 1 | E42: 0 | F42: 0
A43: 1998-03 | B43: d_fuel_power_inflation | C43: -0.8 | D43: 1 | E43: 0 | F43: 0
A44: 1998-03 | B44: d_ppi_inflation | C44: -0.6 | D44: 1 | E44: 0 | F44: 0
A45: 1998-03 | B45: d_cpi_inflation | C45: 0.8 | D45: 1 | E45: 0 | F45: 0
A46: 1998-03 | B46: dlog_import_unit_value | D46: 0 | E46: 0 | F46: 0
A47: 1998-04 | B47: brent_usd_per_bbl | C47: 13.53 | D47: 1 | E47: 1 | F47: 1
A48: 1998-04 | B48: cny_per_usd | C48: 8.3058 | D48: 1 | E48: 1 | F48: 1
A49: 1998-04 | B49: oil_rmb_cny_per_bbl | C49: 112.37747 | D49: 1 | E49: 1 | F49: 1
A50: 1998-04 | B50: fuel_index_yoy | C50: 100.3 | D50: 1 | E50: 1 | F50: 1
A51: 1998-04 | B51: ppi_index_yoy | C51: 96.3 | D51: 1 | E51: 1 | F51: 1
A52: 1998-04 | B52: cpi_index_yoy | C52: 99.7 | D52: 1 | E52: 1 | F52: 1
A53: 1998-04 | B53: purchase_index_yoy | C53: 97.3 | D53: 1 | E53: 1 | F53: 1
A54: 1998-04 | B54: import_quantity_kg | D54: 0 | E54: 1 | F54: 1
A55: 1998-04 | B55: import_value_cny | D55: 0 | E55: 1 | F55: 1
A56: 1998-04 | B56: import_unit_value_cny_per_kg | D56: 0 | E56: 1 | F56: 1
A57: 1998-04 | B57: dlog_oil_rmb | C57: 3.2080519 | D57: 1 | E57: 1 | F57: 1
A58: 1998-04 | B58: d_fuel_power_inflation | C58: -0.4 | D58: 1 | E58: 1 | F58: 1
A59: 1998-04 | B59: d_ppi_inflation | C59: -0.5 | D59: 1 | E59: 1 | F59: 1
A60: 1998-04 | B60: d_cpi_inflation | C60: -1 | D60: 1 | E60: 1 | F60: 1
A61: 1998-04 | B61: dlog_import_unit_value | D61: 0 | E61: 1 | F61: 1
A62: 1998-05 | B62: brent_usd_per_bbl | C62: 14.36 | D62: 1 | E62: 1 | F62: 1
A63: 1998-05 | B63: cny_per_usd | C63: 8.3084 | D63: 1 | E63: 1 | F63: 1
A64: 1998-05 | B64: oil_rmb_cny_per_bbl | C64: 119.30862 | D64: 1 | E64: 1 | F64: 1
A65: 1998-05 | B65: fuel_index_yoy | C65: 98.4 | D65: 1 | E65: 1 | F65: 1
A66: 1998-05 | B66: ppi_index_yoy | C66: 95.5 | D66: 1 | E66: 1 | F66: 1
A67: 1998-05 | B67: cpi_index_yoy | C67: 99 | D67: 1 | E67: 1 | F67: 1
A68: 1998-05 | B68: purchase_index_yoy | C68: 94.7 | D68: 1 | E68: 1 | F68: 1
A69: 1998-05 | B69: import_quantity_kg | D69: 0 | E69: 1 | F69: 1
A70: 1998-05 | B70: import_value_cny | D70: 0 | E70: 1 | F70: 1
A71: 1998-05 | B71: import_unit_value_cny_per_kg | D71: 0 | E71: 1 | F71: 1
A72: 1998-05 | B72: dlog_oil_rmb | C72: 5.9850107 | D72: 1 | E72: 1 | F72: 1
A73: 1998-05 | B73: d_fuel_power_inflation | C73: -1.9 | D73: 1 | E73: 1 | F73: 1
A74: 1998-05 | B74: d_ppi_inflation | C74: -0.8 | D74: 1 | E74: 1 | F74: 1
A75: 1998-05 | B75: d_cpi_inflation | C75: -0.7 | D75: 1 | E75: 1 | F75: 1
A76: 1998-05 | B76: dlog_import_unit_value | D76: 0 | E76: 1 | F76: 1
A77: 1998-06 | B77: brent_usd_per_bbl | C77: 12.21 | D77: 1 | E77: 1 | F77: 1
A78: 1998-06 | B78: cny_per_usd | C78: 8.31 | D78: 1 | E78: 1 | F78: 1
A79: 1998-06 | B79: oil_rmb_cny_per_bbl | C79: 101.4651 | D79: 1 | E79: 1 | F79: 1
A80: 1998-06 | B80: fuel_index_yoy | C80: 98.4 | D80: 1 | E80: 1 | F80: 1
A81: 1998-06 | B81: ppi_index_yoy | C81: 95.1 | D81: 1 | E81: 1 | F81: 1
A82: 1998-06 | B82: cpi_index_yoy | C82: 98.7 | D82: 1 | E82: 1 | F82: 1
A83: 1998-06 | B83: purchase_index_yoy | C83: 94.8 | D83: 1 | E83: 1 | F83: 1
A84: 1998-06 | B84: import_quantity_kg | D84: 0 | E84: 1 | F84: 1
A85: 1998-06 | B85: import_value_cny | D85: 0 | E85: 1 | F85: 1
A86: 1998-06 | B86: import_unit_value_cny_per_kg | D86: 0 | E86: 1 | F86: 1
A87: 1998-06 | B87: dlog_oil_rmb | C87: -16.199872 | D87: 1 | E87: 1 | F87: 1
A88: 1998-06 | B88: d_fuel_power_inflation | C88: 0 | D88: 1 | E88: 1 | F88: 1
A89: 1998-06 | B89: d_ppi_inflation | C89: -0.4 | D89: 1 | E89: 1 | F89: 1
A90: 1998-06 | B90: d_cpi_inflation | C90: -0.3 | D90: 1 | E90: 1 | F90: 1
A91: 1998-06 | B91: dlog_import_unit_value | D91: 0 | E91: 1 | F91: 1
A92: 1998-07 | B92: brent_usd_per_bbl | C92: 12.08 | D92: 1 | E92: 1 | F92: 1
A93: 1998-07 | B93: cny_per_usd | C93: 8.31 | D93: 1 | E93: 1 | F93: 1
A94: 1998-07 | B94: oil_rmb_cny_per_bbl | C94: 100.3848 | D94: 1 | E94: 1 | F94: 1
A95: 1998-07 | B95: fuel_index_yoy | C95: 95.8 | D95: 1 | E95: 1 | F95: 1
A96: 1998-07 | B96: ppi_index_yoy | C96: 95 | D96: 1 | E96: 1 | F96: 1
A97: 1998-07 | B97: cpi_index_yoy | C97: 98.6 | D97: 1 | E97: 1 | F97: 1
A98: 1998-07 | B98: purchase_index_yoy | C98: 94 | D98: 1 | E98: 1 | F98: 1
A99: 1998-07 | B99: import_quantity_kg | D99: 0 | E99: 1 | F99: 1
A100: 1998-07 | B100: import_value_cny | D100: 0 | E100: 1 | F100: 1
...

Sheet Dictionary
A1: variable | B1: units | C1: meaning_and_transformation | D1: provider_or_role
A2: month | B2: YYYY-MM | C2: Monthly calendar, not row-adjacent imputed records | D2: all
A3: brent_usd_per_bbl | B3: USD/barrel | C3: EIA monthly Brent RBRTE, as provided | D3: EIA
A4: cny_per_usd | B4: CNY/USD | C4: FRED EXCHUS monthly average, CNY per USD, no inversion | D4: FRED
A5: oil_rmb_cny_per_bbl | B5: CNY/barrel | C5: brent_usd_per_bbl x cny_per_usd | D5: Derived
A6: dlog_brent | B6: approx % | C6: 100 x ln(Brent_t/Brent_(t-1)) | D6: Derived
A7: dlog_fx | B7: approx % | C7: 100 x ln(FX_t/FX_(t-1)) | D7: Derived
A8: dlog_oil_rmb | B8: approx % | C8: 100 x ln(oil_rmb_t/oil_rmb_(t-1)); exact log identity with Brent and FX | D8: Derived
A9: fuel_index_yoy | B9: index; YoY=100 base | C9: Fuel and power purchase price index, previous-year same month=100 | D9: NBS
A10: ppi_index_yoy | B10: index; YoY=100 base | C10: Industrial producer factory-gate price index | D10: NBS
A11: cpi_index_yoy | B11: index; YoY=100 base | C11: Headline CPI index; four mutually exclusive source-year slices | D11: NBS
A12: d_fuel_power_inflation | B12: percentage points | C12: Fuel index_t-Fuel index_(t-1); monthly change in YoY inflation | D12: Derived
... A28: link1_origin | B28: 0/1 | C28: Fixed lag order p=3 Customs Link 1, origins start May 2015 | D28: Derived
A29: variable | C29: see README
A30: value | C30: see README
A31: available | B31: 0/1 | C31: Observed/defined value available in figure-data long table | D31: Derived
A32: primary_lp_origin_h0 | B32: 0/1 | C32: Macro LP origin eligibility flag for horizon zero | D32: Derived
A33: primary_lp_origin_h12 | B33: 0/1 | C33: Macro LP origin eligibility flag for horizon twelve | D33: Derived

Sheet Source_and_QA
A1: source | B1: series | C1: official_url | D1: distribution_note
A2: EIA Brent | B2: RBRTE | C2: https://www.eia.gov/dnav/pet/hist/LeafHandler.ashx?n=PET&s=RBRTE&f=M | D2: Original provider dataset; check Thomson Reuters credit and terms prior to redistributed supplement.
A3: Federal Reserve / FRED | B3: EXCHUS | C3: https://fred.stlouisfed.org/series/EXCHUS | D3: Monthly EXCHUS observations also included in GitHub release.
A4: NBS China | B4: CPI / PPI / Fuel / industrial purchase / industrial value added | C4: https://data.stats.gov.cn/ | D4: Official monthly query results; downstream reuse conditions must be assessed.
A5: China Customs | B5: HS27090000 monthly imports | C5: https://stats.customs.gov.cn/ | D5: First quantity kg; RMB value CNY; 134 months; conditions of public redistribution are author responsibility.
A7: QA measure | B7: Value
A8: Primary input SHA256 matches | B8: 10 / 10
A9: Calendar months (1998-01–2026-02) | B9: 338
A10: Customs months (2015-01–2026-02) | B10: 134
A11: Eligible LP origin h=0 | B11: 335
A12: Eligible LP origin h=12 | B12: 323
A13: Customs Link1 p=3 observations | B13: 130
A14: Excluded raw CPI placeholders | B14: The source OOXML values 66 and 40 are shared-string indices representing blank cells, not numeric CPI observations. No invalid CPI placeholders were included.
A15: Crude-oil HS code | B15: 27090000
A16: Excluded other customs code | B16: 27102000
A17: Quantitative independence | B17: Raw data -> stationary transformations only; no models refit for this file
A18: Reproduction limits | B18: The reconstructed Figure 2 observations were checked against the frozen 7,774-row source, including coverage, distributions, eligibility indicators and all 64 outliers. The historical source file is not separately redistributed.
